<?xml version="1.0"  encoding="UTF-8" ?>
<pinyin_mapping>
    <item>
        <Hanyu>a</Hanyu>
        <Wade>a</Wade>
        <MPSII>a</MPSII>
        <Yale>a</Yale>
        <Tongyong>a</Tongyong>
        <Phonetic>ㄚ</Phonetic>
    </item>
    <item>
        <Hanyu>ai</Hanyu>
        <Wade>ai</Wade>
        <MPSII>ai</MPSII>
        <Yale>ai</Yale>
        <Tongyong>ai</Tongyong>
        <Phonetic>ㄞ</Phonetic>
    </item>
    <item>
        <Hanyu>an</Hanyu>
        <Wade>an</Wade>
        <MPSII>an</MPSII>
        <Yale>an</Yale>
        <Tongyong>an</Tongyong>
        <Phonetic>ㄢ</Phonetic>
    </item>
    <item>
        <Hanyu>ang</Hanyu>
        <Wade>ang</Wade>
        <MPSII>ang</MPSII>
        <Yale>ang</Yale>
        <Tongyong>ang</Tongyong>
        <Phonetic>ㄤ</Phonetic>
    </item>
    <item>
        <Hanyu>ao</Hanyu>
        <Wade>ao</Wade>
        <MPSII>au</MPSII>
        <Yale>au</Yale>
        <Tongyong>ao</Tongyong>
        <Phonetic>ㄠ</Phonetic>
    </item>
    <item>
        <Hanyu>ba</Hanyu>
        <Wade>pa</Wade>
        <MPSII>ba</MPSII>
        <Yale>ba</Yale>
        <Tongyong>ba</Tongyong>
        <Phonetic>ㄅㄚ</Phonetic>
    </item>
    <item>
        <Hanyu>bai</Hanyu>
        <Wade>pai</Wade>
        <MPSII>bai</MPSII>
        <Yale>bai</Yale>
        <Tongyong>bai</Tongyong>
        <Phonetic>ㄅㄞ</Phonetic>
    </item>
    <item>
        <Hanyu>ban</Hanyu>
        <Wade>pan</Wade>
        <MPSII>ban</MPSII>
        <Yale>ban</Yale>
        <Tongyong>ban</Tongyong>
        <Phonetic>ㄅㄢ</Phonetic>
    </item>
    <item>
        <Hanyu>bang</Hanyu>
        <Wade>pang</Wade>
        <MPSII>bang</MPSII>
        <Yale>bang</Yale>
        <Tongyong>bang</Tongyong>
        <Phonetic>ㄅㄤ</Phonetic>
    </item>
    <item>
        <Hanyu>bao</Hanyu>
        <Wade>pao</Wade>
        <MPSII>bau</MPSII>
        <Yale>bau</Yale>
        <Tongyong>bao</Tongyong>
        <Phonetic>ㄅㄠ</Phonetic>
    </item>
    <item>
        <Hanyu>bei</Hanyu>
        <Wade>pei</Wade>
        <MPSII>bei</MPSII>
        <Yale>bei</Yale>
        <Tongyong>bei</Tongyong>
        <Phonetic>ㄅㄟ</Phonetic>
    </item>
    <item>
        <Hanyu>ben</Hanyu>
        <Wade>pen</Wade>
        <MPSII>ben</MPSII>
        <Yale>ben</Yale>
        <Tongyong>ben</Tongyong>
        <Phonetic>ㄅㄣ</Phonetic>
    </item>
    <item>
        <Hanyu>beng</Hanyu>
        <Wade>peng</Wade>
        <MPSII>beng</MPSII>
        <Yale>beng</Yale>
        <Tongyong>beng</Tongyong>
        <Phonetic>ㄅㄥ</Phonetic>
    </item>
    <item>
        <Hanyu>bi</Hanyu>
        <Wade>pi</Wade>
        <MPSII>bi</MPSII>
        <Yale>bi</Yale>
        <Tongyong>bi</Tongyong>
        <Phonetic>ㄅㄧ</Phonetic>
    </item>
    <item>
        <Hanyu>bian</Hanyu>
        <Wade>pien</Wade>
        <MPSII>bian</MPSII>
        <Yale>byan</Yale>
        <Tongyong>bian</Tongyong>
        <Phonetic>ㄅㄧㄢ</Phonetic>
    </item>
    <item>
        <Hanyu>biao</Hanyu>
        <Wade>piao</Wade>
        <MPSII>biau</MPSII>
        <Yale>byau</Yale>
        <Tongyong>biao</Tongyong>
        <Phonetic>ㄅㄧㄠ</Phonetic>
    </item>
    <item>
        <Hanyu>bie</Hanyu>
        <Wade>pieh</Wade>
        <MPSII>bie</MPSII>
        <Yale>bye</Yale>
        <Tongyong>bie</Tongyong>
        <Phonetic>ㄅㄧㄝ</Phonetic>
    </item>
    <item>
        <Hanyu>bin</Hanyu>
        <Wade>pin</Wade>
        <MPSII>bin</MPSII>
        <Yale>bin</Yale>
        <Tongyong>bin</Tongyong>
        <Phonetic>ㄅㄧㄣ</Phonetic>
    </item>
    <item>
        <Hanyu>bing</Hanyu>
        <Wade>ping</Wade>
        <MPSII>bing</MPSII>
        <Yale>bing</Yale>
        <Tongyong>bing</Tongyong>
        <Phonetic>ㄅㄧㄥ</Phonetic>
    </item>
    <item>
        <Hanyu>bo</Hanyu>
        <Wade>po</Wade>
        <MPSII>bo</MPSII>
        <Yale>bwo</Yale>
        <Tongyong>bo</Tongyong>
        <Phonetic>ㄅㄛ</Phonetic>
    </item>
    <item>
        <Hanyu>bu</Hanyu>
        <Wade>pu</Wade>
        <MPSII>bu</MPSII>
        <Yale>bu</Yale>
        <Tongyong>bu</Tongyong>
        <Phonetic>ㄅㄨ</Phonetic>
    </item>
    <item>
        <Hanyu>ca</Hanyu>
        <Wade>ts`a</Wade>
        <MPSII>tsa</MPSII>
        <Yale>tsa</Yale>
        <Tongyong>ca</Tongyong>
        <Phonetic>ㄘㄚ</Phonetic>
    </item>
    <item>
        <Hanyu>cai</Hanyu>
        <Wade>ts`ai</Wade>
        <MPSII>tsai</MPSII>
        <Yale>tsai</Yale>
        <Tongyong>cai</Tongyong>
        <Phonetic>ㄘㄞ</Phonetic>
    </item>
    <item>
        <Hanyu>can</Hanyu>
        <Wade>ts`an</Wade>
        <MPSII>tsan</MPSII>
        <Yale>tsan</Yale>
        <Tongyong>can</Tongyong>
        <Phonetic>ㄘㄢ</Phonetic>
    </item>
    <item>
        <Hanyu>cang</Hanyu>
        <Wade>ts`ang</Wade>
        <MPSII>tsang</MPSII>
        <Yale>tsang</Yale>
        <Tongyong>cang</Tongyong>
        <Phonetic>ㄘㄤ</Phonetic>
    </item>
    <item>
        <Hanyu>cao</Hanyu>
        <Wade>ts`ao</Wade>
        <MPSII>tsau</MPSII>
        <Yale>tsau</Yale>
        <Tongyong>cao</Tongyong>
        <Phonetic>ㄘㄠ</Phonetic>
    </item>
    <item>
        <Hanyu>ce</Hanyu>
        <Wade>ts`e</Wade>
        <MPSII>tse</MPSII>
        <Yale>tse</Yale>
        <Tongyong>ce</Tongyong>
        <Phonetic>ㄘㄜ</Phonetic>
    </item>
    <item>
        <Hanyu>cen</Hanyu>
        <Wade>ts`en</Wade>
        <MPSII>tsen</MPSII>
        <Yale>tsen</Yale>
        <Tongyong>cen</Tongyong>
        <Phonetic>ㄘㄣ</Phonetic>
    </item>
    <item>
        <Hanyu>ceng</Hanyu>
        <Wade>ts`eng</Wade>
        <MPSII>tseng</MPSII>
        <Yale>tseng</Yale>
        <Tongyong>ceng</Tongyong>
        <Phonetic>ㄘㄥ</Phonetic>
    </item>
    <item>
        <Hanyu>cha</Hanyu>
        <Wade>ch`a</Wade>
        <MPSII>cha</MPSII>
        <Yale>cha</Yale>
        <Tongyong>cha</Tongyong>
        <Phonetic>ㄔㄚ</Phonetic>
    </item>
    <item>
        <Hanyu>chai</Hanyu>
        <Wade>ch`ai</Wade>
        <MPSII>chai</MPSII>
        <Yale>chai</Yale>
        <Tongyong>chai</Tongyong>
        <Phonetic>ㄔㄞ</Phonetic>
    </item>
    <item>
        <Hanyu>chan</Hanyu>
        <Wade>ch`an</Wade>
        <MPSII>chan</MPSII>
        <Yale>chan</Yale>
        <Tongyong>chan</Tongyong>
        <Phonetic>ㄔㄢ</Phonetic>
    </item>
    <item>
        <Hanyu>chang</Hanyu>
        <Wade>ch`ang</Wade>
        <MPSII>chang</MPSII>
        <Yale>chang</Yale>
        <Tongyong>chang</Tongyong>
        <Phonetic>ㄔㄤ</Phonetic>
    </item>
    <item>
        <Hanyu>chao</Hanyu>
        <Wade>ch`ao</Wade>
        <MPSII>chau</MPSII>
        <Yale>chau</Yale>
        <Tongyong>chao</Tongyong>
        <Phonetic>ㄔㄠ</Phonetic>
    </item>
    <item>
        <Hanyu>che</Hanyu>
        <Wade>ch`e</Wade>
        <MPSII>che</MPSII>
        <Yale>che</Yale>
        <Tongyong>che</Tongyong>
        <Phonetic>ㄔㄜ</Phonetic>
    </item>
    <item>
        <Hanyu>chen</Hanyu>
        <Wade>ch`en</Wade>
        <MPSII>chen</MPSII>
        <Yale>chen</Yale>
        <Tongyong>chen</Tongyong>
        <Phonetic>ㄔㄣ</Phonetic>
    </item>
    <item>
        <Hanyu>cheng</Hanyu>
        <Wade>ch`eng</Wade>
        <MPSII>cheng</MPSII>
        <Yale>cheng</Yale>
        <Tongyong>cheng</Tongyong>
        <Phonetic>ㄔㄥ</Phonetic>
    </item>
    <item>
        <Hanyu>chi</Hanyu>
        <Wade>ch`ih</Wade>
        <MPSII>chr</MPSII>
        <Yale>chr</Yale>
        <Tongyong>chih</Tongyong>
        <Phonetic>ㄔ</Phonetic>
    </item>
    <item>
        <Hanyu>chong</Hanyu>
        <Wade>ch`ung</Wade>
        <MPSII>chung</MPSII>
        <Yale>chung</Yale>
        <Tongyong>chong</Tongyong>
        <Phonetic>ㄔㄨㄥ</Phonetic>
    </item>
    <item>
        <Hanyu>chou</Hanyu>
        <Wade>ch`ou</Wade>
        <MPSII>chou</MPSII>
        <Yale>chou</Yale>
        <Tongyong>chou</Tongyong>
        <Phonetic>ㄔㄡ</Phonetic>
    </item>
    <item>
        <Hanyu>chu</Hanyu>
        <Wade>ch`u</Wade>
        <MPSII>chu</MPSII>
        <Yale>chu</Yale>
        <Tongyong>chu</Tongyong>
        <Phonetic>ㄔㄨ</Phonetic>
    </item>
    <item>
        <Hanyu>chua</Hanyu>
        <Wade>ch`ua</Wade>
        <MPSII>chua</MPSII>
        <Yale>chwa</Yale>
        <Tongyong>chua</Tongyong>
        <Phonetic>ㄔㄨㄚ</Phonetic>
    </item>
    <item>
        <Hanyu>chuai</Hanyu>
        <Wade>ch`uai</Wade>
        <MPSII>chuai</MPSII>
        <Yale>chwai</Yale>
        <Tongyong>chuai</Tongyong>
        <Phonetic>ㄔㄨㄞ</Phonetic>
    </item>
    <item>
        <Hanyu>chuan</Hanyu>
        <Wade>ch`uan</Wade>
        <MPSII>chuan</MPSII>
        <Yale>chwan</Yale>
        <Tongyong>chuan</Tongyong>
        <Phonetic>ㄔㄨㄢ</Phonetic>
    </item>
    <item>
        <Hanyu>chuang</Hanyu>
        <Wade>ch`uang</Wade>
        <MPSII>chuang</MPSII>
        <Yale>chwang</Yale>
        <Tongyong>chuang</Tongyong>
        <Phonetic>ㄔㄨㄤ</Phonetic>
    </item>
    <item>
        <Hanyu>chui</Hanyu>
        <Wade>ch`ui</Wade>
        <MPSII>chuei</MPSII>
        <Yale>chwei</Yale>
        <Tongyong>chuei</Tongyong>
        <Phonetic>ㄔㄨㄟ</Phonetic>
    </item>
    <item>
        <Hanyu>chun</Hanyu>
        <Wade>ch`un</Wade>
        <MPSII>chuen</MPSII>
        <Yale>chwen</Yale>
        <Tongyong>chun</Tongyong>
        <Phonetic>ㄔㄨㄣ</Phonetic>
    </item>
    <item>
        <Hanyu>chuo</Hanyu>
        <Wade>ch`o</Wade>
        <MPSII>chuo</MPSII>
        <Yale>chwo</Yale>
        <Tongyong>chuo</Tongyong>
        <Phonetic>ㄔㄨㄛ</Phonetic>
    </item>
    <item>
        <Hanyu>qi</Hanyu>
        <Wade>ch`i</Wade>
        <MPSII>chi</MPSII>
        <Yale>chi</Yale>
        <Tongyong>ci</Tongyong>
        <Phonetic>ㄑㄧ</Phonetic>
    </item>
    <item>
        <Hanyu>qia</Hanyu>
        <Wade>ch`ia</Wade>
        <MPSII>chia</MPSII>
        <Yale>chya</Yale>
        <Tongyong>cia</Tongyong>
        <Phonetic>ㄑㄧㄚ</Phonetic>
    </item>
    <item>
        <Hanyu>qian</Hanyu>
        <Wade>ch`ien</Wade>
        <MPSII>chian</MPSII>
        <Yale>chyan</Yale>
        <Tongyong>cian</Tongyong>
        <Phonetic>ㄑㄧㄢ</Phonetic>
    </item>
    <item>
        <Hanyu>qiang</Hanyu>
        <Wade>ch`iang</Wade>
        <MPSII>chiang</MPSII>
        <Yale>chyang</Yale>
        <Tongyong>ciang</Tongyong>
        <Phonetic>ㄑㄧㄤ</Phonetic>
    </item>
    <item>
        <Hanyu>qiao</Hanyu>
        <Wade>ch`iao</Wade>
        <MPSII>chiau</MPSII>
        <Yale>chyau</Yale>
        <Tongyong>ciao</Tongyong>
        <Phonetic>ㄑㄧㄠ</Phonetic>
    </item>
    <item>
        <Hanyu>qie</Hanyu>
        <Wade>ch`ieh</Wade>
        <MPSII>chie</MPSII>
        <Yale>chye</Yale>
        <Tongyong>cie</Tongyong>
        <Phonetic>ㄑㄧㄝ</Phonetic>
    </item>
    <item>
        <Hanyu>ci</Hanyu>
        <Wade>tz`u</Wade>
        <MPSII>tsz</MPSII>
        <Yale>tsz</Yale>
        <Tongyong>cih</Tongyong>
        <Phonetic>ㄘ</Phonetic>
    </item>
    <item>
        <Hanyu>qin</Hanyu>
        <Wade>ch`in</Wade>
        <MPSII>chin</MPSII>
        <Yale>chin</Yale>
        <Tongyong>cin</Tongyong>
        <Phonetic>ㄑㄧㄣ</Phonetic>
    </item>
    <item>
        <Hanyu>qing</Hanyu>
        <Wade>ch`ing</Wade>
        <MPSII>ching</MPSII>
        <Yale>ching</Yale>
        <Tongyong>cing</Tongyong>
        <Phonetic>ㄑㄧㄥ</Phonetic>
    </item>
    <item>
        <Hanyu>qiu</Hanyu>
        <Wade>ch`iu</Wade>
        <MPSII>chiou</MPSII>
        <Yale>chyou</Yale>
        <Tongyong>ciou</Tongyong>
        <Phonetic>ㄑㄧㄡ</Phonetic>
    </item>
    <item>
        <Hanyu>cong</Hanyu>
        <Wade>ts`ung</Wade>
        <MPSII>tsung</MPSII>
        <Yale>tsung</Yale>
        <Tongyong>cong</Tongyong>
        <Phonetic>ㄘㄨㄥ</Phonetic>
    </item>
    <item>
        <Hanyu>cou</Hanyu>
        <Wade>ts`ou</Wade>
        <MPSII>tsou</MPSII>
        <Yale>tsou</Yale>
        <Tongyong>cou</Tongyong>
        <Phonetic>ㄘㄡ</Phonetic>
    </item>
    <item>
        <Hanyu>cu</Hanyu>
        <Wade>ts`u</Wade>
        <MPSII>tsu</MPSII>
        <Yale>tsu</Yale>
        <Tongyong>cu</Tongyong>
        <Phonetic>ㄘㄨ</Phonetic>
    </item>
    <item>
        <Hanyu>cuan</Hanyu>
        <Wade>ts`uan</Wade>
        <MPSII>tsuan</MPSII>
        <Yale>tswan</Yale>
        <Tongyong>cuan</Tongyong>
        <Phonetic>ㄘㄨㄢ</Phonetic>
    </item>
    <item>
        <Hanyu>cui</Hanyu>
        <Wade>ts`ui</Wade>
        <MPSII>tsuei</MPSII>
        <Yale>tswei</Yale>
        <Tongyong>cuei</Tongyong>
        <Phonetic>ㄘㄨㄟ</Phonetic>
    </item>
    <item>
        <Hanyu>cun</Hanyu>
        <Wade>ts`un</Wade>
        <MPSII>tsuen</MPSII>
        <Yale>tswen</Yale>
        <Tongyong>cun</Tongyong>
        <Phonetic>ㄘㄨㄣ</Phonetic>
    </item>
    <item>
        <Hanyu>cuo</Hanyu>
        <Wade>ts`o</Wade>
        <MPSII>tsuo</MPSII>
        <Yale>tswo</Yale>
        <Tongyong>cuo</Tongyong>
        <Phonetic>ㄘㄨㄛ</Phonetic>
    </item>
    <item>
        <Hanyu>qiong</Hanyu>
        <Wade>ch`iung</Wade>
        <MPSII>chiung</MPSII>
        <Yale>chyung</Yale>
        <Tongyong>cyong</Tongyong>
        <Phonetic>ㄑㄩㄥ</Phonetic>
    </item>
    <item>
        <Hanyu>qu</Hanyu>
        <Wade>ch`u:</Wade>
        <MPSII>chiu</MPSII>
        <Yale>chyu</Yale>
        <Tongyong>cyu</Tongyong>
        <Phonetic>ㄑㄩ</Phonetic>
    </item>
    <item>
        <Hanyu>quan</Hanyu>
        <Wade>ch`u:an</Wade>
        <MPSII>chiuan</MPSII>
        <Yale>chywan</Yale>
        <Tongyong>cyuan</Tongyong>
        <Phonetic>ㄑㄨㄢ</Phonetic>
    </item>
    <item>
        <Hanyu>que</Hanyu>
        <Wade>ch`u:eh</Wade>
        <MPSII>chiue</MPSII>
        <Yale>chywe</Yale>
        <Tongyong>cyue</Tongyong>
        <Phonetic>ㄑㄩㄜ</Phonetic>
    </item>
    <item>
        <Hanyu>qun</Hanyu>
        <Wade>ch`u:n</Wade>
        <MPSII>chiun</MPSII>
        <Yale>chyun</Yale>
        <Tongyong>cyun</Tongyong>
        <Phonetic>ㄑㄩㄋ</Phonetic>
    </item>
    <item>
        <Hanyu>da</Hanyu>
        <Wade>ta</Wade>
        <MPSII>da</MPSII>
        <Yale>da</Yale>
        <Tongyong>da</Tongyong>
        <Phonetic>ㄉㄚ</Phonetic>
    </item>
    <item>
        <Hanyu>dai</Hanyu>
        <Wade>tai</Wade>
        <MPSII>dai</MPSII>
        <Yale>dai</Yale>
        <Tongyong>dai</Tongyong>
        <Phonetic>ㄉㄞ</Phonetic>
    </item>
    <item>
        <Hanyu>dan</Hanyu>
        <Wade>tan</Wade>
        <MPSII>dan</MPSII>
        <Yale>dan</Yale>
        <Tongyong>dan</Tongyong>
        <Phonetic>ㄉㄢ</Phonetic>
    </item>
    <item>
        <Hanyu>dang</Hanyu>
        <Wade>tang</Wade>
        <MPSII>dang</MPSII>
        <Yale>dang</Yale>
        <Tongyong>dang</Tongyong>
        <Phonetic>ㄉㄤ</Phonetic>
    </item>
    <item>
        <Hanyu>dao</Hanyu>
        <Wade>tao</Wade>
        <MPSII>dau</MPSII>
        <Yale>dau</Yale>
        <Tongyong>dao</Tongyong>
        <Phonetic>ㄉㄠ</Phonetic>
    </item>
    <item>
        <Hanyu>de</Hanyu>
        <Wade>te</Wade>
        <MPSII>de</MPSII>
        <Yale>de</Yale>
        <Tongyong>de</Tongyong>
        <Phonetic>ㄉㄜ</Phonetic>
    </item>
    <item>
        <Hanyu>dei</Hanyu>
        <Wade>tei</Wade>
        <MPSII>dei</MPSII>
        <Yale>dei</Yale>
        <Tongyong>dei</Tongyong>
        <Phonetic>ㄉㄟ</Phonetic>
    </item>
    <item>
        <Hanyu>den</Hanyu>
        <Wade>ten</Wade>
        <MPSII>den</MPSII>
        <Yale>den</Yale>
        <Tongyong>den</Tongyong>
        <Phonetic>ㄉㄣ</Phonetic>
    </item>
    <item>
        <Hanyu>deng</Hanyu>
        <Wade>teng</Wade>
        <MPSII>deng</MPSII>
        <Yale>deng</Yale>
        <Tongyong>deng</Tongyong>
        <Phonetic>ㄉㄥ</Phonetic>
    </item>
    <item>
        <Hanyu>di</Hanyu>
        <Wade>ti</Wade>
        <MPSII>di</MPSII>
        <Yale>di</Yale>
        <Tongyong>di</Tongyong>
        <Phonetic>ㄉㄧ</Phonetic>
    </item>
    <item>
        <Hanyu>dian</Hanyu>
        <Wade>tien</Wade>
        <MPSII>dian</MPSII>
        <Yale>dyan</Yale>
        <Tongyong>dian</Tongyong>
        <Phonetic>ㄉㄧㄢ</Phonetic>
    </item>
    <item>
        <Hanyu>diang</Hanyu>
        <Wade>tiang</Wade>
        <MPSII>diang</MPSII>
        <Yale>dyang</Yale>
        <Tongyong>diang</Tongyong>
        <Phonetic>ㄉㄧㄤ</Phonetic>
    </item>
    <item>
        <Hanyu>diao</Hanyu>
        <Wade>tiao</Wade>
        <MPSII>diau</MPSII>
        <Yale>dyau</Yale>
        <Tongyong>diao</Tongyong>
        <Phonetic>ㄉㄧㄠ</Phonetic>
    </item>
    <item>
        <Hanyu>die</Hanyu>
        <Wade>tieh</Wade>
        <MPSII>die</MPSII>
        <Yale>dye</Yale>
        <Tongyong>die</Tongyong>
        <Phonetic>ㄉㄧㄝ</Phonetic>
    </item>
    <item>
        <Hanyu>ding</Hanyu>
        <Wade>ting</Wade>
        <MPSII>ding</MPSII>
        <Yale>ding</Yale>
        <Tongyong>ding</Tongyong>
        <Phonetic>ㄉㄧㄥ</Phonetic>
    </item>
    <item>
        <Hanyu>diu</Hanyu>
        <Wade>tiu</Wade>
        <MPSII>diou</MPSII>
        <Yale>dyou</Yale>
        <Tongyong>diou</Tongyong>
        <Phonetic>ㄉㄧㄡ</Phonetic>
    </item>
    <item>
        <Hanyu>dong</Hanyu>
        <Wade>tung</Wade>
        <MPSII>dung</MPSII>
        <Yale>dung</Yale>
        <Tongyong>dong</Tongyong>
        <Phonetic>ㄉㄨㄥ</Phonetic>
    </item>
    <item>
        <Hanyu>dou</Hanyu>
        <Wade>tou</Wade>
        <MPSII>dou</MPSII>
        <Yale>dou</Yale>
        <Tongyong>dou</Tongyong>
        <Phonetic>ㄉㄡ</Phonetic>
    </item>
    <item>
        <Hanyu>du</Hanyu>
        <Wade>tu</Wade>
        <MPSII>du</MPSII>
        <Yale>du</Yale>
        <Tongyong>du</Tongyong>
        <Phonetic>ㄉㄨ</Phonetic>
    </item>
    <item>
        <Hanyu>duan</Hanyu>
        <Wade>tuan</Wade>
        <MPSII>duan</MPSII>
        <Yale>dwan</Yale>
        <Tongyong>duan</Tongyong>
        <Phonetic>ㄉㄨㄢ</Phonetic>
    </item>
    <item>
        <Hanyu>dui</Hanyu>
        <Wade>tui</Wade>
        <MPSII>duei</MPSII>
        <Yale>dwei</Yale>
        <Tongyong>duei</Tongyong>
        <Phonetic>ㄉㄨㄟ</Phonetic>
    </item>
    <item>
        <Hanyu>dun</Hanyu>
        <Wade>tun</Wade>
        <MPSII>duen</MPSII>
        <Yale>dwen</Yale>
        <Tongyong>dun</Tongyong>
        <Phonetic>ㄉㄨㄣ</Phonetic>
    </item>
    <item>
        <Hanyu>duo</Hanyu>
        <Wade>to</Wade>
        <MPSII>duo</MPSII>
        <Yale>dwo</Yale>
        <Tongyong>duo</Tongyong>
        <Phonetic>ㄉㄨㄛ</Phonetic>
    </item>
    <item>
        <Hanyu>e</Hanyu>
        <Wade>e</Wade>
        <MPSII>e</MPSII>
        <Yale>e</Yale>
        <Tongyong>e</Tongyong>
        <Phonetic>ㄜ</Phonetic>
    </item>
    <item>
        <Hanyu>ei</Hanyu>
        <Wade>ei</Wade>
        <MPSII>ei</MPSII>
        <Yale>ei</Yale>
        <Tongyong>ei</Tongyong>
        <Phonetic>ㄟ</Phonetic>
    </item>
    <item>
        <Hanyu>en</Hanyu>
        <Wade>en</Wade>
        <MPSII>en</MPSII>
        <Yale>en</Yale>
        <Tongyong>en</Tongyong>
        <Phonetic>ㄣ</Phonetic>
    </item>
    <item>
        <Hanyu>er</Hanyu>
        <Wade>erh</Wade>
        <MPSII>er</MPSII>
        <Yale>er</Yale>
        <Tongyong>er</Tongyong>
        <Phonetic>ㄦ</Phonetic>
    </item>
    <item>
        <Hanyu>fa</Hanyu>
        <Wade>fa</Wade>
        <MPSII>fa</MPSII>
        <Yale>fa</Yale>
        <Tongyong>fa</Tongyong>
        <Phonetic>ㄈㄚ</Phonetic>
    </item>
    <item>
        <Hanyu>fan</Hanyu>
        <Wade>fan</Wade>
        <MPSII>fan</MPSII>
        <Yale>fan</Yale>
        <Tongyong>fan</Tongyong>
        <Phonetic>ㄈㄢ</Phonetic>
    </item>
    <item>
        <Hanyu>fang</Hanyu>
        <Wade>fang</Wade>
        <MPSII>fang</MPSII>
        <Yale>fang</Yale>
        <Tongyong>fang</Tongyong>
        <Phonetic>ㄈㄤ</Phonetic>
    </item>
    <item>
        <Hanyu>fei</Hanyu>
        <Wade>fei</Wade>
        <MPSII>fei</MPSII>
        <Yale>fei</Yale>
        <Tongyong>fei</Tongyong>
        <Phonetic>ㄈㄟ</Phonetic>
    </item>
    <item>
        <Hanyu>fen</Hanyu>
        <Wade>fen</Wade>
        <MPSII>fen</MPSII>
        <Yale>fen</Yale>
        <Tongyong>fen</Tongyong>
        <Phonetic>ㄈㄣ</Phonetic>
    </item>
    <item>
        <Hanyu>fo</Hanyu>
        <Wade>fo</Wade>
        <MPSII>fo</MPSII>
        <Yale>fwo</Yale>
        <Tongyong>fo</Tongyong>
        <Phonetic>ㄈㄛ</Phonetic>
    </item>
    <item>
        <Hanyu>feng</Hanyu>
        <Wade>feng</Wade>
        <MPSII>feng</MPSII>
        <Yale>feng</Yale>
        <Tongyong>fong</Tongyong>
        <Phonetic>ㄈㄥ</Phonetic>
    </item>
    <item>
        <Hanyu>fou</Hanyu>
        <Wade>fou</Wade>
        <MPSII>fou</MPSII>
        <Yale>fou</Yale>
        <Tongyong>fou</Tongyong>
        <Phonetic>ㄈㄡ</Phonetic>
    </item>
    <item>
        <Hanyu>fu</Hanyu>
        <Wade>fu</Wade>
        <MPSII>fu</MPSII>
        <Yale>fu</Yale>
        <Tongyong>fu</Tongyong>
        <Phonetic>ㄈㄨ</Phonetic>
    </item>
    <item>
        <Hanyu>ga</Hanyu>
        <Wade>ka</Wade>
        <MPSII>ga</MPSII>
        <Yale>ga</Yale>
        <Tongyong>ga</Tongyong>
        <Phonetic>ㄍㄚ</Phonetic>
    </item>
    <item>
        <Hanyu>gai</Hanyu>
        <Wade>kai</Wade>
        <MPSII>gai</MPSII>
        <Yale>gai</Yale>
        <Tongyong>gai</Tongyong>
        <Phonetic>ㄍㄞ</Phonetic>
    </item>
    <item>
        <Hanyu>gan</Hanyu>
        <Wade>kan</Wade>
        <MPSII>gan</MPSII>
        <Yale>gan</Yale>
        <Tongyong>gan</Tongyong>
        <Phonetic>ㄍㄢ</Phonetic>
    </item>
    <item>
        <Hanyu>gang</Hanyu>
        <Wade>kang</Wade>
        <MPSII>gang</MPSII>
        <Yale>gang</Yale>
        <Tongyong>gang</Tongyong>
        <Phonetic>ㄍㄤ</Phonetic>
    </item>
    <item>
        <Hanyu>gao</Hanyu>
        <Wade>kao</Wade>
        <MPSII>gau</MPSII>
        <Yale>gau</Yale>
        <Tongyong>gao</Tongyong>
        <Phonetic>ㄍㄠ</Phonetic>
    </item>
    <item>
        <Hanyu>ge</Hanyu>
        <Wade>ko</Wade>
        <MPSII>ge</MPSII>
        <Yale>ge</Yale>
        <Tongyong>ge</Tongyong>
        <Phonetic>ㄍㄜ</Phonetic>
    </item>
    <item>
        <Hanyu>gei</Hanyu>
        <Wade>kei</Wade>
        <MPSII>gei</MPSII>
        <Yale>gei</Yale>
        <Tongyong>gei</Tongyong>
        <Phonetic>ㄍㄟ</Phonetic>
    </item>
    <item>
        <Hanyu>gen</Hanyu>
        <Wade>ken</Wade>
        <MPSII>gen</MPSII>
        <Yale>gen</Yale>
        <Tongyong>gen</Tongyong>
        <Phonetic>ㄍㄣ</Phonetic>
    </item>
    <item>
        <Hanyu>geng</Hanyu>
        <Wade>keng</Wade>
        <MPSII>geng</MPSII>
        <Yale>geng</Yale>
        <Tongyong>geng</Tongyong>
        <Phonetic>ㄍㄥ</Phonetic>
    </item>
    <item>
        <Hanyu>gong</Hanyu>
        <Wade>kung</Wade>
        <MPSII>gung</MPSII>
        <Yale>gung</Yale>
        <Tongyong>gong</Tongyong>
        <Phonetic>ㄍㄨㄥ</Phonetic>
    </item>
    <item>
        <Hanyu>gou</Hanyu>
        <Wade>kou</Wade>
        <MPSII>gou</MPSII>
        <Yale>gou</Yale>
        <Tongyong>gou</Tongyong>
        <Phonetic>ㄍㄡ</Phonetic>
    </item>
    <item>
        <Hanyu>gu</Hanyu>
        <Wade>ku</Wade>
        <MPSII>gu</MPSII>
        <Yale>gu</Yale>
        <Tongyong>gu</Tongyong>
        <Phonetic>ㄍㄨ</Phonetic>
    </item>
    <item>
        <Hanyu>gua</Hanyu>
        <Wade>kua</Wade>
        <MPSII>gua</MPSII>
        <Yale>gwa</Yale>
        <Tongyong>gua</Tongyong>
        <Phonetic>ㄍㄨㄚ</Phonetic>
    </item>
    <item>
        <Hanyu>guai</Hanyu>
        <Wade>kuai</Wade>
        <MPSII>guai</MPSII>
        <Yale>gwai</Yale>
        <Tongyong>guai</Tongyong>
        <Phonetic>ㄍㄨㄞ</Phonetic>
    </item>
    <item>
        <Hanyu>guan</Hanyu>
        <Wade>kuan</Wade>
        <MPSII>guan</MPSII>
        <Yale>gwan</Yale>
        <Tongyong>guan</Tongyong>
        <Phonetic>ㄍㄨㄢ</Phonetic>
    </item>
    <item>
        <Hanyu>guang</Hanyu>
        <Wade>kuang</Wade>
        <MPSII>guang</MPSII>
        <Yale>gwang</Yale>
        <Tongyong>guang</Tongyong>
        <Phonetic>ㄍㄨㄤ</Phonetic>
    </item>
    <item>
        <Hanyu>gui</Hanyu>
        <Wade>kuei</Wade>
        <MPSII>guei</MPSII>
        <Yale>gwei</Yale>
        <Tongyong>guei</Tongyong>
        <Phonetic>ㄍㄨㄟ</Phonetic>
    </item>
    <item>
        <Hanyu>gun</Hanyu>
        <Wade>kun</Wade>
        <MPSII>guen</MPSII>
        <Yale>gwun</Yale>
        <Tongyong>gun</Tongyong>
        <Phonetic>ㄍㄨㄣ</Phonetic>
    </item>
    <item>
        <Hanyu>guo</Hanyu>
        <Wade>kuo</Wade>
        <MPSII>guo</MPSII>
        <Yale>gwo</Yale>
        <Tongyong>guo</Tongyong>
        <Phonetic>ㄍㄨㄛ</Phonetic>
    </item>
    <item>
        <Hanyu>ha</Hanyu>
        <Wade>ha</Wade>
        <MPSII>ha</MPSII>
        <Yale>ha</Yale>
        <Tongyong>ha</Tongyong>
        <Phonetic>ㄏㄚ</Phonetic>
    </item>
    <item>
        <Hanyu>hai</Hanyu>
        <Wade>hai</Wade>
        <MPSII>hai</MPSII>
        <Yale>hai</Yale>
        <Tongyong>hai</Tongyong>
        <Phonetic>ㄏㄞ</Phonetic>
    </item>
    <item>
        <Hanyu>han</Hanyu>
        <Wade>han</Wade>
        <MPSII>han</MPSII>
        <Yale>han</Yale>
        <Tongyong>han</Tongyong>
        <Phonetic>ㄏㄢ</Phonetic>
    </item>
    <item>
        <Hanyu>hang</Hanyu>
        <Wade>hang</Wade>
        <MPSII>hang</MPSII>
        <Yale>hang</Yale>
        <Tongyong>hang</Tongyong>
        <Phonetic>ㄏㄤ</Phonetic>
    </item>
    <item>
        <Hanyu>hao</Hanyu>
        <Wade>hao</Wade>
        <MPSII>hau</MPSII>
        <Yale>hau</Yale>
        <Tongyong>hao</Tongyong>
        <Phonetic>ㄏㄠ</Phonetic>
    </item>
    <item>
        <Hanyu>he</Hanyu>
        <Wade>ho</Wade>
        <MPSII>he</MPSII>
        <Yale>he</Yale>
        <Tongyong>he</Tongyong>
        <Phonetic>ㄏㄜ</Phonetic>
    </item>
    <item>
        <Hanyu>hei</Hanyu>
        <Wade>hei</Wade>
        <MPSII>hei</MPSII>
        <Yale>hei</Yale>
        <Tongyong>hei</Tongyong>
        <Phonetic>ㄏㄟ</Phonetic>
    </item>
    <item>
        <Hanyu>hen</Hanyu>
        <Wade>hen</Wade>
        <MPSII>hen</MPSII>
        <Yale>hen</Yale>
        <Tongyong>hen</Tongyong>
        <Phonetic>ㄏㄣ</Phonetic>
    </item>
    <item>
        <Hanyu>heng</Hanyu>
        <Wade>heng</Wade>
        <MPSII>heng</MPSII>
        <Yale>heng</Yale>
        <Tongyong>heng</Tongyong>
        <Phonetic>ㄏㄥ</Phonetic>
    </item>
    <item>
        <Hanyu>hong</Hanyu>
        <Wade>hung</Wade>
        <MPSII>hung</MPSII>
        <Yale>hung</Yale>
        <Tongyong>hong</Tongyong>
        <Phonetic>ㄏㄨㄥ</Phonetic>
    </item>
    <item>
        <Hanyu>hou</Hanyu>
        <Wade>hou</Wade>
        <MPSII>hou</MPSII>
        <Yale>hou</Yale>
        <Tongyong>hou</Tongyong>
        <Phonetic>ㄏㄡ</Phonetic>
    </item>
    <item>
        <Hanyu>hu</Hanyu>
        <Wade>hu</Wade>
        <MPSII>hu</MPSII>
        <Yale>hu</Yale>
        <Tongyong>hu</Tongyong>
        <Phonetic>ㄏㄨ</Phonetic>
    </item>
    <item>
        <Hanyu>hua</Hanyu>
        <Wade>hua</Wade>
        <MPSII>hua</MPSII>
        <Yale>hwa</Yale>
        <Tongyong>hua</Tongyong>
        <Phonetic>ㄏㄨㄚ</Phonetic>
    </item>
    <item>
        <Hanyu>huai</Hanyu>
        <Wade>huai</Wade>
        <MPSII>huai</MPSII>
        <Yale>hwai</Yale>
        <Tongyong>huai</Tongyong>
        <Phonetic>ㄏㄨㄞ</Phonetic>
    </item>
    <item>
        <Hanyu>huan</Hanyu>
        <Wade>huan</Wade>
        <MPSII>huan</MPSII>
        <Yale>hwan</Yale>
        <Tongyong>huan</Tongyong>
        <Phonetic>ㄏㄨㄢ</Phonetic>
    </item>
    <item>
        <Hanyu>huang</Hanyu>
        <Wade>huang</Wade>
        <MPSII>huang</MPSII>
        <Yale>hwang</Yale>
        <Tongyong>huang</Tongyong>
        <Phonetic>ㄏㄨㄤ</Phonetic>
    </item>
    <item>
        <Hanyu>hui</Hanyu>
        <Wade>hui</Wade>
        <MPSII>huei</MPSII>
        <Yale>hwei</Yale>
        <Tongyong>huei</Tongyong>
        <Phonetic>ㄏㄨㄟ</Phonetic>
    </item>
    <item>
        <Hanyu>hun</Hanyu>
        <Wade>hun</Wade>
        <MPSII>huen</MPSII>
        <Yale>hwen</Yale>
        <Tongyong>hun</Tongyong>
        <Phonetic>ㄏㄨㄣ</Phonetic>
    </item>
    <item>
        <Hanyu>huo</Hanyu>
        <Wade>huo</Wade>
        <MPSII>huo</MPSII>
        <Yale>hwo</Yale>
        <Tongyong>huo</Tongyong>
        <Phonetic>ㄏㄨㄛ</Phonetic>
    </item>
    <item>
        <Hanyu>zha</Hanyu>
        <Wade>cha</Wade>
        <MPSII>ja</MPSII>
        <Yale>ja</Yale>
        <Tongyong>jha</Tongyong>
        <Phonetic>ㄓㄚ</Phonetic>
    </item>
    <item>
        <Hanyu>zhai</Hanyu>
        <Wade>chai</Wade>
        <MPSII>jai</MPSII>
        <Yale>jai</Yale>
        <Tongyong>jhai</Tongyong>
        <Phonetic>ㄓㄞ</Phonetic>
    </item>
    <item>
        <Hanyu>zhan</Hanyu>
        <Wade>chan</Wade>
        <MPSII>jan</MPSII>
        <Yale>jan</Yale>
        <Tongyong>jhan</Tongyong>
        <Phonetic>ㄓㄢ</Phonetic>
    </item>
    <item>
        <Hanyu>zhang</Hanyu>
        <Wade>chang</Wade>
        <MPSII>jang</MPSII>
        <Yale>jang</Yale>
        <Tongyong>jhang</Tongyong>
        <Phonetic>ㄓㄤ</Phonetic>
    </item>
    <item>
        <Hanyu>zhao</Hanyu>
        <Wade>chao</Wade>
        <MPSII>jau</MPSII>
        <Yale>jau</Yale>
        <Tongyong>jhao</Tongyong>
        <Phonetic>ㄓㄠ</Phonetic>
    </item>
    <item>
        <Hanyu>zhe</Hanyu>
        <Wade>che</Wade>
        <MPSII>je</MPSII>
        <Yale>je</Yale>
        <Tongyong>jhe</Tongyong>
        <Phonetic>ㄓㄜ</Phonetic>
    </item>
    <item>
        <Hanyu>zhei</Hanyu>
        <Wade>chei</Wade>
        <MPSII>jei</MPSII>
        <Yale>jei</Yale>
        <Tongyong>jhei</Tongyong>
        <Phonetic>ㄓㄟ</Phonetic>
    </item>
    <item>
        <Hanyu>zhen</Hanyu>
        <Wade>chen</Wade>
        <MPSII>jen</MPSII>
        <Yale>jen</Yale>
        <Tongyong>jhen</Tongyong>
        <Phonetic>ㄓㄣ</Phonetic>
    </item>
    <item>
        <Hanyu>zheng</Hanyu>
        <Wade>cheng</Wade>
        <MPSII>jeng</MPSII>
        <Yale>jeng</Yale>
        <Tongyong>jheng</Tongyong>
        <Phonetic>ㄓㄥ</Phonetic>
    </item>
    <item>
        <Hanyu>zhi</Hanyu>
        <Wade>chih</Wade>
        <MPSII>jr</MPSII>
        <Yale>jr</Yale>
        <Tongyong>jhih</Tongyong>
        <Phonetic>ㄓ</Phonetic>
    </item>
    <item>
        <Hanyu>zhong</Hanyu>
        <Wade>chung</Wade>
        <MPSII>jung</MPSII>
        <Yale>jung</Yale>
        <Tongyong>jhong</Tongyong>
        <Phonetic>ㄓㄨㄥ</Phonetic>
    </item>
    <item>
        <Hanyu>zhou</Hanyu>
        <Wade>chou</Wade>
        <MPSII>jou</MPSII>
        <Yale>jou</Yale>
        <Tongyong>jhou</Tongyong>
        <Phonetic>ㄓㄡ</Phonetic>
    </item>
    <item>
        <Hanyu>zhu</Hanyu>
        <Wade>chu</Wade>
        <MPSII>ju</MPSII>
        <Yale>ju</Yale>
        <Tongyong>jhu</Tongyong>
        <Phonetic>ㄓㄨ</Phonetic>
    </item>
    <item>
        <Hanyu>zhua</Hanyu>
        <Wade>chua</Wade>
        <MPSII>jua</MPSII>
        <Yale>jwa</Yale>
        <Tongyong>jhua</Tongyong>
        <Phonetic>ㄓㄨㄚ</Phonetic>
    </item>
    <item>
        <Hanyu>zhuai</Hanyu>
        <Wade>chuai</Wade>
        <MPSII>juai</MPSII>
        <Yale>jwai</Yale>
        <Tongyong>jhuai</Tongyong>
        <Phonetic>ㄓㄨㄞ</Phonetic>
    </item>
    <item>
        <Hanyu>zhuan</Hanyu>
        <Wade>chuan</Wade>
        <MPSII>juan</MPSII>
        <Yale>jwan</Yale>
        <Tongyong>jhuan</Tongyong>
        <Phonetic>ㄓㄨㄢ</Phonetic>
    </item>
    <item>
        <Hanyu>zhuang</Hanyu>
        <Wade>chuang</Wade>
        <MPSII>juang</MPSII>
        <Yale>jwang</Yale>
        <Tongyong>jhuang</Tongyong>
        <Phonetic>ㄓㄨㄤ</Phonetic>
    </item>
    <item>
        <Hanyu>zhui</Hanyu>
        <Wade>chui</Wade>
        <MPSII>juei</MPSII>
        <Yale>jwei</Yale>
        <Tongyong>jhuei</Tongyong>
        <Phonetic>ㄓㄨㄟ</Phonetic>
    </item>
    <item>
        <Hanyu>zhun</Hanyu>
        <Wade>chun</Wade>
        <MPSII>juen</MPSII>
        <Yale>jwen</Yale>
        <Tongyong>jhun</Tongyong>
        <Phonetic>ㄓㄨㄣ</Phonetic>
    </item>
    <item>
        <Hanyu>zhuo</Hanyu>
        <Wade>cho</Wade>
        <MPSII>juo</MPSII>
        <Yale>jwo</Yale>
        <Tongyong>jhuo</Tongyong>
        <Phonetic>ㄓㄨㄛ</Phonetic>
    </item>
    <item>
        <Hanyu>ji</Hanyu>
        <Wade>chi</Wade>
        <MPSII>ji</MPSII>
        <Yale>ji</Yale>
        <Tongyong>ji</Tongyong>
        <Phonetic>ㄐㄧ</Phonetic>
    </item>
    <item>
        <Hanyu>jia</Hanyu>
        <Wade>chia</Wade>
        <MPSII>jia</MPSII>
        <Yale>jya</Yale>
        <Tongyong>jia</Tongyong>
        <Phonetic>ㄐㄧㄚ</Phonetic>
    </item>
    <item>
        <Hanyu>jian</Hanyu>
        <Wade>chien</Wade>
        <MPSII>jian</MPSII>
        <Yale>jyan</Yale>
        <Tongyong>jian</Tongyong>
        <Phonetic>ㄐㄧㄢ</Phonetic>
    </item>
    <item>
        <Hanyu>jiang</Hanyu>
        <Wade>chiang</Wade>
        <MPSII>jiang</MPSII>
        <Yale>jyang</Yale>
        <Tongyong>jiang</Tongyong>
        <Phonetic>ㄐㄧㄤ</Phonetic>
    </item>
    <item>
        <Hanyu>jiao</Hanyu>
        <Wade>chiao</Wade>
        <MPSII>jiau</MPSII>
        <Yale>jyau</Yale>
        <Tongyong>jiao</Tongyong>
        <Phonetic>ㄐㄧㄠ</Phonetic>
    </item>
    <item>
        <Hanyu>jie</Hanyu>
        <Wade>chieh</Wade>
        <MPSII>jie</MPSII>
        <Yale>jye</Yale>
        <Tongyong>jie</Tongyong>
        <Phonetic>ㄐㄧㄝ</Phonetic>
    </item>
    <item>
        <Hanyu>jin</Hanyu>
        <Wade>chin</Wade>
        <MPSII>jin</MPSII>
        <Yale>jin</Yale>
        <Tongyong>jin</Tongyong>
        <Phonetic>ㄐㄧㄣ</Phonetic>
    </item>
    <item>
        <Hanyu>jing</Hanyu>
        <Wade>ching</Wade>
        <MPSII>jing</MPSII>
        <Yale>jing</Yale>
        <Tongyong>jing</Tongyong>
        <Phonetic>ㄐㄧㄥ</Phonetic>
    </item>
    <item>
        <Hanyu>jiu</Hanyu>
        <Wade>chiu</Wade>
        <MPSII>jiou</MPSII>
        <Yale>jyou</Yale>
        <Tongyong>jiou</Tongyong>
        <Phonetic>ㄐㄧㄡ</Phonetic>
    </item>
    <item>
        <Hanyu>jiong</Hanyu>
        <Wade>chiung</Wade>
        <MPSII>jiung</MPSII>
        <Yale>jyung</Yale>
        <Tongyong>jyong</Tongyong>
        <Phonetic>ㄐㄩㄥ</Phonetic>
    </item>
    <item>
        <Hanyu>ju</Hanyu>
        <Wade>chu:</Wade>
        <MPSII>jiu</MPSII>
        <Yale>jyu</Yale>
        <Tongyong>jyu</Tongyong>
        <Phonetic>ㄐㄩ</Phonetic>
    </item>
    <item>
        <Hanyu>juan</Hanyu>
        <Wade>chu:an</Wade>
        <MPSII>jiuan</MPSII>
        <Yale>jywan</Yale>
        <Tongyong>jyuan</Tongyong>
        <Phonetic>ㄐㄨㄢ</Phonetic>
    </item>
    <item>
        <Hanyu>jue</Hanyu>
        <Wade>chu:eh</Wade>
        <MPSII>jiue</MPSII>
        <Yale>jywe</Yale>
        <Tongyong>jyue</Tongyong>
        <Phonetic>ㄐㄩㄜ</Phonetic>
    </item>
    <item>
        <Hanyu>jun</Hanyu>
        <Wade>chu:n</Wade>
        <MPSII>jiun</MPSII>
        <Yale>jyun</Yale>
        <Tongyong>jyun</Tongyong>
        <Phonetic>ㄐㄩㄋ</Phonetic>
    </item>
    <item>
        <Hanyu>ka</Hanyu>
        <Wade>k`a</Wade>
        <MPSII>ka</MPSII>
        <Yale>ka</Yale>
        <Tongyong>ka</Tongyong>
        <Phonetic>ㄎㄚ</Phonetic>
    </item>
    <item>
        <Hanyu>kai</Hanyu>
        <Wade>k`ai</Wade>
        <MPSII>kai</MPSII>
        <Yale>kai</Yale>
        <Tongyong>kai</Tongyong>
        <Phonetic>ㄎㄞ</Phonetic>
    </item>
    <item>
        <Hanyu>kan</Hanyu>
        <Wade>k`an</Wade>
        <MPSII>kan</MPSII>
        <Yale>kan</Yale>
        <Tongyong>kan</Tongyong>
        <Phonetic>ㄎㄢ</Phonetic>
    </item>
    <item>
        <Hanyu>kang</Hanyu>
        <Wade>k`ang</Wade>
        <MPSII>kang</MPSII>
        <Yale>kang</Yale>
        <Tongyong>kang</Tongyong>
        <Phonetic>ㄎㄤ</Phonetic>
    </item>
    <item>
        <Hanyu>kao</Hanyu>
        <Wade>k`ao</Wade>
        <MPSII>kau</MPSII>
        <Yale>kau</Yale>
        <Tongyong>kao</Tongyong>
        <Phonetic>ㄎㄠ</Phonetic>
    </item>
    <item>
        <Hanyu>ke</Hanyu>
        <Wade>k`o</Wade>
        <MPSII>ke</MPSII>
        <Yale>ke</Yale>
        <Tongyong>ke</Tongyong>
        <Phonetic>ㄎㄜ</Phonetic>
    </item>
    <item>
        <Hanyu>ken</Hanyu>
        <Wade>k`en</Wade>
        <MPSII>ken</MPSII>
        <Yale>ken</Yale>
        <Tongyong>ken</Tongyong>
        <Phonetic>ㄎㄣ</Phonetic>
    </item>
    <item>
        <Hanyu>keng</Hanyu>
        <Wade>k`eng</Wade>
        <MPSII>keng</MPSII>
        <Yale>keng</Yale>
        <Tongyong>keng</Tongyong>
        <Phonetic>ㄎㄥ</Phonetic>
    </item>
    <item>
        <Hanyu>kong</Hanyu>
        <Wade>k`ung</Wade>
        <MPSII>kung</MPSII>
        <Yale>kung</Yale>
        <Tongyong>kong</Tongyong>
        <Phonetic>ㄎㄨㄥ</Phonetic>
    </item>
    <item>
        <Hanyu>kou</Hanyu>
        <Wade>k`ou</Wade>
        <MPSII>kou</MPSII>
        <Yale>kou</Yale>
        <Tongyong>kou</Tongyong>
        <Phonetic>ㄎㄡ</Phonetic>
    </item>
    <item>
        <Hanyu>ku</Hanyu>
        <Wade>k`u</Wade>
        <MPSII>ku</MPSII>
        <Yale>ku</Yale>
        <Tongyong>ku</Tongyong>
        <Phonetic>ㄎㄨ</Phonetic>
    </item>
    <item>
        <Hanyu>kua</Hanyu>
        <Wade>k`ua</Wade>
        <MPSII>kua</MPSII>
        <Yale>kwa</Yale>
        <Tongyong>kua</Tongyong>
        <Phonetic>ㄎㄨㄚ</Phonetic>
    </item>
    <item>
        <Hanyu>kuai</Hanyu>
        <Wade>k`uai</Wade>
        <MPSII>kuai</MPSII>
        <Yale>kwai</Yale>
        <Tongyong>kuai</Tongyong>
        <Phonetic>ㄎㄨㄞ</Phonetic>
    </item>
    <item>
        <Hanyu>kuan</Hanyu>
        <Wade>k`uan</Wade>
        <MPSII>kuan</MPSII>
        <Yale>kwan</Yale>
        <Tongyong>kuan</Tongyong>
        <Phonetic>ㄎㄨㄢ</Phonetic>
    </item>
    <item>
        <Hanyu>kuang</Hanyu>
        <Wade>k`uang</Wade>
        <MPSII>kuang</MPSII>
        <Yale>kwang</Yale>
        <Tongyong>kuang</Tongyong>
        <Phonetic>ㄎㄨㄤ</Phonetic>
    </item>
    <item>
        <Hanyu>kui</Hanyu>
        <Wade>k`uei</Wade>
        <MPSII>kuei</MPSII>
        <Yale>kwei</Yale>
        <Tongyong>kuei</Tongyong>
        <Phonetic>ㄎㄨㄟ</Phonetic>
    </item>
    <item>
        <Hanyu>kun</Hanyu>
        <Wade>k`un</Wade>
        <MPSII>kuen</MPSII>
        <Yale>kwen</Yale>
        <Tongyong>kun</Tongyong>
        <Phonetic>ㄎㄨㄣ</Phonetic>
    </item>
    <item>
        <Hanyu>kuo</Hanyu>
        <Wade>k`uo</Wade>
        <MPSII>kuo</MPSII>
        <Yale>kwo</Yale>
        <Tongyong>kuo</Tongyong>
        <Phonetic>ㄎㄨㄛ</Phonetic>
    </item>
    <item>
        <Hanyu>la</Hanyu>
        <Wade>la</Wade>
        <MPSII>la</MPSII>
        <Yale>la</Yale>
        <Tongyong>la</Tongyong>
        <Phonetic>ㄌㄚ</Phonetic>
    </item>
    <item>
        <Hanyu>lai</Hanyu>
        <Wade>lai</Wade>
        <MPSII>lai</MPSII>
        <Yale>lai</Yale>
        <Tongyong>lai</Tongyong>
        <Phonetic>ㄌㄞ</Phonetic>
    </item>
    <item>
        <Hanyu>lan</Hanyu>
        <Wade>lan</Wade>
        <MPSII>lan</MPSII>
        <Yale>lan</Yale>
        <Tongyong>lan</Tongyong>
        <Phonetic>ㄌㄢ</Phonetic>
    </item>
    <item>
        <Hanyu>lang</Hanyu>
        <Wade>lang</Wade>
        <MPSII>lang</MPSII>
        <Yale>lang</Yale>
        <Tongyong>lang</Tongyong>
        <Phonetic>ㄌㄤ</Phonetic>
    </item>
    <item>
        <Hanyu>lao</Hanyu>
        <Wade>lao</Wade>
        <MPSII>lau</MPSII>
        <Yale>lau</Yale>
        <Tongyong>lao</Tongyong>
        <Phonetic>ㄌㄠ</Phonetic>
    </item>
    <item>
        <Hanyu>le</Hanyu>
        <Wade>le</Wade>
        <MPSII>le</MPSII>
        <Yale>le</Yale>
        <Tongyong>le</Tongyong>
        <Phonetic>ㄌㄜ</Phonetic>
    </item>
    <item>
        <Hanyu>lei</Hanyu>
        <Wade>lei</Wade>
        <MPSII>lei</MPSII>
        <Yale>lei</Yale>
        <Tongyong>lei</Tongyong>
        <Phonetic>ㄌㄟ</Phonetic>
    </item>
    <item>
        <Hanyu>leng</Hanyu>
        <Wade>leng</Wade>
        <MPSII>leng</MPSII>
        <Yale>leng</Yale>
        <Tongyong>leng</Tongyong>
        <Phonetic>ㄌㄥ</Phonetic>
    </item>
    <item>
        <Hanyu>li</Hanyu>
        <Wade>li</Wade>
        <MPSII>li</MPSII>
        <Yale>li</Yale>
        <Tongyong>li</Tongyong>
        <Phonetic>ㄌㄧ</Phonetic>
    </item>
    <item>
        <Hanyu>lia</Hanyu>
        <Wade>lia</Wade>
        <MPSII>lia</MPSII>
        <Yale>lya</Yale>
        <Tongyong>lia</Tongyong>
        <Phonetic>ㄌㄧㄚ</Phonetic>
    </item>
    <item>
        <Hanyu>lian</Hanyu>
        <Wade>lien</Wade>
        <MPSII>lian</MPSII>
        <Yale>lyan</Yale>
        <Tongyong>lian</Tongyong>
        <Phonetic>ㄌㄧㄢ</Phonetic>
    </item>
    <item>
        <Hanyu>liang</Hanyu>
        <Wade>liang</Wade>
        <MPSII>liang</MPSII>
        <Yale>lyang</Yale>
        <Tongyong>liang</Tongyong>
        <Phonetic>ㄌㄧㄤ</Phonetic>
    </item>
    <item>
        <Hanyu>liao</Hanyu>
        <Wade>liao</Wade>
        <MPSII>liau</MPSII>
        <Yale>lyau</Yale>
        <Tongyong>liao</Tongyong>
        <Phonetic>ㄌㄧㄠ</Phonetic>
    </item>
    <item>
        <Hanyu>lie</Hanyu>
        <Wade>lieh</Wade>
        <MPSII>lie</MPSII>
        <Yale>lye</Yale>
        <Tongyong>lie</Tongyong>
        <Phonetic>ㄌㄧㄝ</Phonetic>
    </item>
    <item>
        <Hanyu>lin</Hanyu>
        <Wade>lin</Wade>
        <MPSII>lin</MPSII>
        <Yale>lin</Yale>
        <Tongyong>lin</Tongyong>
        <Phonetic>ㄌㄧㄣ</Phonetic>
    </item>
    <item>
        <Hanyu>ling</Hanyu>
        <Wade>ling</Wade>
        <MPSII>ling</MPSII>
        <Yale>ling</Yale>
        <Tongyong>ling</Tongyong>
        <Phonetic>ㄌㄧㄥ</Phonetic>
    </item>
    <item>
        <Hanyu>liu</Hanyu>
        <Wade>liu</Wade>
        <MPSII>liou</MPSII>
        <Yale>lyou</Yale>
        <Tongyong>liou</Tongyong>
        <Phonetic>ㄌㄧㄡ</Phonetic>
    </item>
    <item>
        <Hanyu>lo</Hanyu>
        <Wade>lo</Wade>
        <MPSII>lo</MPSII>
        <Yale>lo</Yale>
        <Tongyong>lo</Tongyong>
        <Phonetic>ㄌㄛ</Phonetic>
    </item>
    <item>
        <Hanyu>long</Hanyu>
        <Wade>lung</Wade>
        <MPSII>lung</MPSII>
        <Yale>lung</Yale>
        <Tongyong>long</Tongyong>
        <Phonetic>ㄌㄨㄥ</Phonetic>
    </item>
    <item>
        <Hanyu>lou</Hanyu>
        <Wade>lou</Wade>
        <MPSII>lou</MPSII>
        <Yale>lou</Yale>
        <Tongyong>lou</Tongyong>
        <Phonetic>ㄌㄡ</Phonetic>
    </item>
    <item>
        <Hanyu>lu</Hanyu>
        <Wade>lu</Wade>
        <MPSII>lu</MPSII>
        <Yale>lu</Yale>
        <Tongyong>lu</Tongyong>
        <Phonetic>ㄌㄨ</Phonetic>
    </item>
    <item>
        <Hanyu>luan</Hanyu>
        <Wade>luan</Wade>
        <MPSII>luan</MPSII>
        <Yale>lwan</Yale>
        <Tongyong>luan</Tongyong>
        <Phonetic>ㄌㄨㄢ</Phonetic>
    </item>
    <item>
        <Hanyu>lun</Hanyu>
        <Wade>lun</Wade>
        <MPSII>luen</MPSII>
        <Yale>lwun</Yale>
        <Tongyong>lun</Tongyong>
        <Phonetic>ㄌㄨㄣ</Phonetic>
    </item>
    <item>
        <Hanyu>luo</Hanyu>
        <Wade>lo</Wade>
        <MPSII>luo</MPSII>
        <Yale>lwo</Yale>
        <Tongyong>luo</Tongyong>
        <Phonetic>ㄌㄨㄛ</Phonetic>
    </item>
    <item>
        <Hanyu>lu:</Hanyu>
        <Wade>lu:</Wade>
        <MPSII>liu</MPSII>
        <Yale>lyu</Yale>
        <Tongyong>lyu</Tongyong>
        <Phonetic>ㄌㄩ</Phonetic>
    </item>
    <item>
        <Hanyu>lu:e</Hanyu>
        <Wade>lu:eh</Wade>
        <MPSII>liue</MPSII>
        <Yale>lywe</Yale>
        <Tongyong>lyue</Tongyong>
        <Phonetic>ㄌㄩㄝ</Phonetic>
    </item>
    <item>
        <Hanyu>lu:n</Hanyu>
        <Wade>lu:n</Wade>
        <MPSII>liun</MPSII>
        <Yale>lyun</Yale>
        <Tongyong>lyun</Tongyong>
        <Phonetic>ㄌㄩㄣ</Phonetic>
    </item>
    <item>
        <Hanyu>ma</Hanyu>
        <Wade>ma</Wade>
        <MPSII>ma</MPSII>
        <Yale>ma</Yale>
        <Tongyong>ma</Tongyong>
        <Phonetic>ㄇㄚ</Phonetic>
    </item>
    <item>
        <Hanyu>mai</Hanyu>
        <Wade>mai</Wade>
        <MPSII>mai</MPSII>
        <Yale>mai</Yale>
        <Tongyong>mai</Tongyong>
        <Phonetic>ㄇㄞ</Phonetic>
    </item>
    <item>
        <Hanyu>man</Hanyu>
        <Wade>man</Wade>
        <MPSII>man</MPSII>
        <Yale>man</Yale>
        <Tongyong>man</Tongyong>
        <Phonetic>ㄇㄢ</Phonetic>
    </item>
    <item>
        <Hanyu>mang</Hanyu>
        <Wade>mang</Wade>
        <MPSII>mang</MPSII>
        <Yale>mang</Yale>
        <Tongyong>mang</Tongyong>
        <Phonetic>ㄇㄤ</Phonetic>
    </item>
    <item>
        <Hanyu>mao</Hanyu>
        <Wade>mao</Wade>
        <MPSII>mau</MPSII>
        <Yale>mau</Yale>
        <Tongyong>mao</Tongyong>
        <Phonetic>ㄇㄠ</Phonetic>
    </item>
    <item>
        <Hanyu>me</Hanyu>
        <Wade>me</Wade>
        <MPSII>me</MPSII>
        <Yale>me</Yale>
        <Tongyong>me</Tongyong>
        <Phonetic>ㄇㄜ</Phonetic>
    </item>
    <item>
        <Hanyu>mei</Hanyu>
        <Wade>mei</Wade>
        <MPSII>mei</MPSII>
        <Yale>mei</Yale>
        <Tongyong>mei</Tongyong>
        <Phonetic>ㄇㄟ</Phonetic>
    </item>
    <item>
        <Hanyu>men</Hanyu>
        <Wade>men</Wade>
        <MPSII>men</MPSII>
        <Yale>men</Yale>
        <Tongyong>men</Tongyong>
        <Phonetic>ㄇㄣ</Phonetic>
    </item>
    <item>
        <Hanyu>meng</Hanyu>
        <Wade>meng</Wade>
        <MPSII>meng</MPSII>
        <Yale>meng</Yale>
        <Tongyong>meng</Tongyong>
        <Phonetic>ㄇㄥ</Phonetic>
    </item>
    <item>
        <Hanyu>mi</Hanyu>
        <Wade>mi</Wade>
        <MPSII>mi</MPSII>
        <Yale>mi</Yale>
        <Tongyong>mi</Tongyong>
        <Phonetic>ㄇㄧ</Phonetic>
    </item>
    <item>
        <Hanyu>mian</Hanyu>
        <Wade>mien</Wade>
        <MPSII>mian</MPSII>
        <Yale>myan</Yale>
        <Tongyong>mian</Tongyong>
        <Phonetic>ㄇㄧㄢ</Phonetic>
    </item>
    <item>
        <Hanyu>miao</Hanyu>
        <Wade>miao</Wade>
        <MPSII>miau</MPSII>
        <Yale>myau</Yale>
        <Tongyong>miao</Tongyong>
        <Phonetic>ㄇㄧㄠ</Phonetic>
    </item>
    <item>
        <Hanyu>mie</Hanyu>
        <Wade>mieh</Wade>
        <MPSII>mie</MPSII>
        <Yale>mye</Yale>
        <Tongyong>mie</Tongyong>
        <Phonetic>ㄇㄧㄝ</Phonetic>
    </item>
    <item>
        <Hanyu>min</Hanyu>
        <Wade>min</Wade>
        <MPSII>min</MPSII>
        <Yale>min</Yale>
        <Tongyong>min</Tongyong>
        <Phonetic>ㄇㄧㄣ</Phonetic>
    </item>
    <item>
        <Hanyu>ming</Hanyu>
        <Wade>ming</Wade>
        <MPSII>ming</MPSII>
        <Yale>ming</Yale>
        <Tongyong>ming</Tongyong>
        <Phonetic>ㄇㄧㄥ</Phonetic>
    </item>
    <item>
        <Hanyu>miu</Hanyu>
        <Wade>miu</Wade>
        <MPSII>miou</MPSII>
        <Yale>myou</Yale>
        <Tongyong>miou</Tongyong>
        <Phonetic>ㄇㄧㄡ</Phonetic>
    </item>
    <item>
        <Hanyu>mo</Hanyu>
        <Wade>mo</Wade>
        <MPSII>mo</MPSII>
        <Yale>mwo</Yale>
        <Tongyong>mo</Tongyong>
        <Phonetic>ㄇㄛ</Phonetic>
    </item>
    <item>
        <Hanyu>mou</Hanyu>
        <Wade>mou</Wade>
        <MPSII>mou</MPSII>
        <Yale>mou</Yale>
        <Tongyong>mou</Tongyong>
        <Phonetic>ㄇㄡ</Phonetic>
    </item>
    <item>
        <Hanyu>mu</Hanyu>
        <Wade>mu</Wade>
        <MPSII>mu</MPSII>
        <Yale>mu</Yale>
        <Tongyong>mu</Tongyong>
        <Phonetic>ㄇㄨ</Phonetic>
    </item>
    <item>
        <Hanyu>na</Hanyu>
        <Wade>na</Wade>
        <MPSII>na</MPSII>
        <Yale>na</Yale>
        <Tongyong>na</Tongyong>
        <Phonetic>ㄋㄚ</Phonetic>
    </item>
    <item>
        <Hanyu>nai</Hanyu>
        <Wade>nai</Wade>
        <MPSII>nai</MPSII>
        <Yale>nai</Yale>
        <Tongyong>nai</Tongyong>
        <Phonetic>ㄋㄞ</Phonetic>
    </item>
    <item>
        <Hanyu>nan</Hanyu>
        <Wade>nan</Wade>
        <MPSII>nan</MPSII>
        <Yale>nan</Yale>
        <Tongyong>nan</Tongyong>
        <Phonetic>ㄋㄢ</Phonetic>
    </item>
    <item>
        <Hanyu>nang</Hanyu>
        <Wade>nang</Wade>
        <MPSII>nang</MPSII>
        <Yale>nang</Yale>
        <Tongyong>nang</Tongyong>
        <Phonetic>ㄋㄤ</Phonetic>
    </item>
    <item>
        <Hanyu>nao</Hanyu>
        <Wade>nao</Wade>
        <MPSII>nau</MPSII>
        <Yale>nau</Yale>
        <Tongyong>nao</Tongyong>
        <Phonetic>ㄋㄠ</Phonetic>
    </item>
    <item>
        <Hanyu>ne</Hanyu>
        <Wade>ne</Wade>
        <MPSII>ne</MPSII>
        <Yale>ne</Yale>
        <Tongyong>ne</Tongyong>
        <Phonetic>ㄋㄜ</Phonetic>
    </item>
    <item>
        <Hanyu>nei</Hanyu>
        <Wade>nei</Wade>
        <MPSII>nei</MPSII>
        <Yale>nei</Yale>
        <Tongyong>nei</Tongyong>
        <Phonetic>ㄋㄟ</Phonetic>
    </item>
    <item>
        <Hanyu>nen</Hanyu>
        <Wade>nen</Wade>
        <MPSII>nen</MPSII>
        <Yale>nen</Yale>
        <Tongyong>nen</Tongyong>
        <Phonetic>ㄋㄣ</Phonetic>
    </item>
    <item>
        <Hanyu>neng</Hanyu>
        <Wade>neng</Wade>
        <MPSII>neng</MPSII>
        <Yale>neng</Yale>
        <Tongyong>neng</Tongyong>
        <Phonetic>ㄋㄥ</Phonetic>
    </item>
    <item>
        <Hanyu>ni</Hanyu>
        <Wade>ni</Wade>
        <MPSII>ni</MPSII>
        <Yale>ni</Yale>
        <Tongyong>ni</Tongyong>
        <Phonetic>ㄋㄧ</Phonetic>
    </item>
    <item>
        <Hanyu>nia</Hanyu>
        <Wade>nia</Wade>
        <MPSII>nia</MPSII>
        <Yale>nya</Yale>
        <Tongyong>nia</Tongyong>
        <Phonetic>ㄋㄧㄚ</Phonetic>
    </item>
    <item>
        <Hanyu>nian</Hanyu>
        <Wade>nien</Wade>
        <MPSII>nian</MPSII>
        <Yale>nyan</Yale>
        <Tongyong>nian</Tongyong>
        <Phonetic>ㄋㄧㄢ</Phonetic>
    </item>
    <item>
        <Hanyu>niang</Hanyu>
        <Wade>niang</Wade>
        <MPSII>niang</MPSII>
        <Yale>nyang</Yale>
        <Tongyong>niang</Tongyong>
        <Phonetic>ㄋㄧㄤ</Phonetic>
    </item>
    <item>
        <Hanyu>niao</Hanyu>
        <Wade>niao</Wade>
        <MPSII>niau</MPSII>
        <Yale>nyau</Yale>
        <Tongyong>niao</Tongyong>
        <Phonetic>ㄋㄧㄠ</Phonetic>
    </item>
    <item>
        <Hanyu>nie</Hanyu>
        <Wade>nieh</Wade>
        <MPSII>nie</MPSII>
        <Yale>nye</Yale>
        <Tongyong>nie</Tongyong>
        <Phonetic>ㄋㄧㄝ</Phonetic>
    </item>
    <item>
        <Hanyu>nin</Hanyu>
        <Wade>nin</Wade>
        <MPSII>nin</MPSII>
        <Yale>nin</Yale>
        <Tongyong>nin</Tongyong>
        <Phonetic>ㄋㄧㄣ</Phonetic>
    </item>
    <item>
        <Hanyu>ning</Hanyu>
        <Wade>ning</Wade>
        <MPSII>ning</MPSII>
        <Yale>ning</Yale>
        <Tongyong>ning</Tongyong>
        <Phonetic>ㄋㄧㄥ</Phonetic>
    </item>
    <item>
        <Hanyu>niu</Hanyu>
        <Wade>niu</Wade>
        <MPSII>niou</MPSII>
        <Yale>nyou</Yale>
        <Tongyong>niou</Tongyong>
        <Phonetic>ㄋㄧㄡ</Phonetic>
    </item>
    <item>
        <Hanyu>nong</Hanyu>
        <Wade>nung</Wade>
        <MPSII>nung</MPSII>
        <Yale>nung</Yale>
        <Tongyong>nong</Tongyong>
        <Phonetic>ㄋㄨㄥ</Phonetic>
    </item>
    <item>
        <Hanyu>nou</Hanyu>
        <Wade>nou</Wade>
        <MPSII>nou</MPSII>
        <Yale>nou</Yale>
        <Tongyong>nou</Tongyong>
        <Phonetic>ㄋㄡ</Phonetic>
    </item>
    <item>
        <Hanyu>nu</Hanyu>
        <Wade>nu</Wade>
        <MPSII>nu</MPSII>
        <Yale>nu</Yale>
        <Tongyong>nu</Tongyong>
        <Phonetic>ㄋㄨ</Phonetic>
    </item>
    <item>
        <Hanyu>nuan</Hanyu>
        <Wade>nuan</Wade>
        <MPSII>nuan</MPSII>
        <Yale>nwan</Yale>
        <Tongyong>nuan</Tongyong>
        <Phonetic>ㄋㄨㄢ</Phonetic>
    </item>
    <item>
        <Hanyu>nun</Hanyu>
        <Wade>nun</Wade>
        <MPSII>nuen</MPSII>
        <Yale>nwen</Yale>
        <Tongyong>nun</Tongyong>
        <Phonetic>ㄋㄨㄣ</Phonetic>
    </item>
    <item>
        <Hanyu>nuo</Hanyu>
        <Wade>no</Wade>
        <MPSII>nuo</MPSII>
        <Yale>nwo</Yale>
        <Tongyong>nuo</Tongyong>
        <Phonetic>ㄋㄨㄛ</Phonetic>
    </item>
    <item>
        <Hanyu>nu:</Hanyu>
        <Wade>nu:</Wade>
        <MPSII>niu</MPSII>
        <Yale>nyu</Yale>
        <Tongyong>nyu</Tongyong>
        <Phonetic>ㄋㄩ</Phonetic>
    </item>
    <item>
        <Hanyu>nu:e</Hanyu>
        <Wade>nu:eh</Wade>
        <MPSII>niue</MPSII>
        <Yale>nywe</Yale>
        <Tongyong>nyue</Tongyong>
        <Phonetic>ㄋㄩㄝ</Phonetic>
    </item>
    <item>
        <Hanyu>ou</Hanyu>
        <Wade>ou</Wade>
        <MPSII>ou</MPSII>
        <Yale>ou</Yale>
        <Tongyong>ou</Tongyong>
        <Phonetic>ㄡ</Phonetic>
    </item>
    <item>
        <Hanyu>pa</Hanyu>
        <Wade>p`a</Wade>
        <MPSII>pa</MPSII>
        <Yale>pa</Yale>
        <Tongyong>pa</Tongyong>
        <Phonetic>ㄆㄚ</Phonetic>
    </item>
    <item>
        <Hanyu>pai</Hanyu>
        <Wade>p`ai</Wade>
        <MPSII>pai</MPSII>
        <Yale>pai</Yale>
        <Tongyong>pai</Tongyong>
        <Phonetic>ㄆㄞ</Phonetic>
    </item>
    <item>
        <Hanyu>pan</Hanyu>
        <Wade>p`an</Wade>
        <MPSII>pan</MPSII>
        <Yale>pan</Yale>
        <Tongyong>pan</Tongyong>
        <Phonetic>ㄆㄢ</Phonetic>
    </item>
    <item>
        <Hanyu>pang</Hanyu>
        <Wade>p`ang</Wade>
        <MPSII>pang</MPSII>
        <Yale>pang</Yale>
        <Tongyong>pang</Tongyong>
        <Phonetic>ㄆㄤ</Phonetic>
    </item>
    <item>
        <Hanyu>pao</Hanyu>
        <Wade>p`ao</Wade>
        <MPSII>pau</MPSII>
        <Yale>pau</Yale>
        <Tongyong>pao</Tongyong>
        <Phonetic>ㄆㄠ</Phonetic>
    </item>
    <item>
        <Hanyu>pei</Hanyu>
        <Wade>p`ei</Wade>
        <MPSII>pei</MPSII>
        <Yale>pei</Yale>
        <Tongyong>pei</Tongyong>
        <Phonetic>ㄆㄟ</Phonetic>
    </item>
    <item>
        <Hanyu>pen</Hanyu>
        <Wade>p`en</Wade>
        <MPSII>pen</MPSII>
        <Yale>pen</Yale>
        <Tongyong>pen</Tongyong>
        <Phonetic>ㄆㄣ</Phonetic>
    </item>
    <item>
        <Hanyu>peng</Hanyu>
        <Wade>p`eng</Wade>
        <MPSII>peng</MPSII>
        <Yale>peng</Yale>
        <Tongyong>peng</Tongyong>
        <Phonetic>ㄆㄥ</Phonetic>
    </item>
    <item>
        <Hanyu>pi</Hanyu>
        <Wade>p`i</Wade>
        <MPSII>pi</MPSII>
        <Yale>pi</Yale>
        <Tongyong>pi</Tongyong>
        <Phonetic>ㄆㄧ</Phonetic>
    </item>
    <item>
        <Hanyu>pian</Hanyu>
        <Wade>p`ien</Wade>
        <MPSII>pian</MPSII>
        <Yale>pyan</Yale>
        <Tongyong>pian</Tongyong>
        <Phonetic>ㄆㄧㄢ</Phonetic>
    </item>
    <item>
        <Hanyu>piao</Hanyu>
        <Wade>p`iao</Wade>
        <MPSII>piau</MPSII>
        <Yale>pyau</Yale>
        <Tongyong>piao</Tongyong>
        <Phonetic>ㄆㄧㄠ</Phonetic>
    </item>
    <item>
        <Hanyu>pie</Hanyu>
        <Wade>p`ieh</Wade>
        <MPSII>pie</MPSII>
        <Yale>pye</Yale>
        <Tongyong>pie</Tongyong>
        <Phonetic>ㄆㄧㄝ</Phonetic>
    </item>
    <item>
        <Hanyu>pin</Hanyu>
        <Wade>p`in</Wade>
        <MPSII>pin</MPSII>
        <Yale>pin</Yale>
        <Tongyong>pin</Tongyong>
        <Phonetic>ㄆㄧㄣ</Phonetic>
    </item>
    <item>
        <Hanyu>ping</Hanyu>
        <Wade>p`ing</Wade>
        <MPSII>ping</MPSII>
        <Yale>ping</Yale>
        <Tongyong>ping</Tongyong>
        <Phonetic>ㄆㄧㄥ</Phonetic>
    </item>
    <item>
        <Hanyu>po</Hanyu>
        <Wade>p`o</Wade>
        <MPSII>po</MPSII>
        <Yale>pwo</Yale>
        <Tongyong>po</Tongyong>
        <Phonetic>ㄆㄛ</Phonetic>
    </item>
    <item>
        <Hanyu>pou</Hanyu>
        <Wade>p`ou</Wade>
        <MPSII>pou</MPSII>
        <Yale>pou</Yale>
        <Tongyong>pou</Tongyong>
        <Phonetic>ㄆㄡ</Phonetic>
    </item>
    <item>
        <Hanyu>pu</Hanyu>
        <Wade>p`u</Wade>
        <MPSII>pu</MPSII>
        <Yale>pu</Yale>
        <Tongyong>pu</Tongyong>
        <Phonetic>ㄆㄨ</Phonetic>
    </item>
    <item>
        <Hanyu>ran</Hanyu>
        <Wade>jan</Wade>
        <MPSII>ran</MPSII>
        <Yale>ran</Yale>
        <Tongyong>ran</Tongyong>
        <Phonetic>ㄖㄢ</Phonetic>
    </item>
    <item>
        <Hanyu>rang</Hanyu>
        <Wade>jang</Wade>
        <MPSII>rang</MPSII>
        <Yale>rang</Yale>
        <Tongyong>rang</Tongyong>
        <Phonetic>ㄖㄤ</Phonetic>
    </item>
    <item>
        <Hanyu>rao</Hanyu>
        <Wade>jao</Wade>
        <MPSII>rau</MPSII>
        <Yale>rau</Yale>
        <Tongyong>rao</Tongyong>
        <Phonetic>ㄖㄠ</Phonetic>
    </item>
    <item>
        <Hanyu>re</Hanyu>
        <Wade>je</Wade>
        <MPSII>re</MPSII>
        <Yale>re</Yale>
        <Tongyong>re</Tongyong>
        <Phonetic>ㄖㄜ</Phonetic>
    </item>
    <item>
        <Hanyu>ren</Hanyu>
        <Wade>jen</Wade>
        <MPSII>ren</MPSII>
        <Yale>ren</Yale>
        <Tongyong>ren</Tongyong>
        <Phonetic>ㄖㄣ</Phonetic>
    </item>
    <item>
        <Hanyu>reng</Hanyu>
        <Wade>jeng</Wade>
        <MPSII>reng</MPSII>
        <Yale>reng</Yale>
        <Tongyong>reng</Tongyong>
        <Phonetic>ㄖㄥ</Phonetic>
    </item>
    <item>
        <Hanyu>ri</Hanyu>
        <Wade>jih</Wade>
        <MPSII>r</MPSII>
        <Yale>r</Yale>
        <Tongyong>rih</Tongyong>
        <Phonetic>ㄖ</Phonetic>
    </item>
    <item>
        <Hanyu>rong</Hanyu>
        <Wade>jung</Wade>
        <MPSII>rung</MPSII>
        <Yale>rung</Yale>
        <Tongyong>rong</Tongyong>
        <Phonetic>ㄖㄨㄥ</Phonetic>
    </item>
    <item>
        <Hanyu>rou</Hanyu>
        <Wade>jou</Wade>
        <MPSII>rou</MPSII>
        <Yale>rou</Yale>
        <Tongyong>rou</Tongyong>
        <Phonetic>ㄖㄡ</Phonetic>
    </item>
    <item>
        <Hanyu>ru</Hanyu>
        <Wade>ju</Wade>
        <MPSII>ru</MPSII>
        <Yale>ru</Yale>
        <Tongyong>ru</Tongyong>
        <Phonetic>ㄖㄨ</Phonetic>
    </item>
    <item>
        <Hanyu>ruan</Hanyu>
        <Wade>juan</Wade>
        <MPSII>ruan</MPSII>
        <Yale>rwan</Yale>
        <Tongyong>ruan</Tongyong>
        <Phonetic>ㄖㄨㄢ</Phonetic>
    </item>
    <item>
        <Hanyu>rui</Hanyu>
        <Wade>jui</Wade>
        <MPSII>ruei</MPSII>
        <Yale>rwei</Yale>
        <Tongyong>ruei</Tongyong>
        <Phonetic>ㄖㄨㄟ</Phonetic>
    </item>
    <item>
        <Hanyu>run</Hanyu>
        <Wade>jun</Wade>
        <MPSII>ruen</MPSII>
        <Yale>rwun</Yale>
        <Tongyong>run</Tongyong>
        <Phonetic>ㄖㄨㄣ</Phonetic>
    </item>
    <item>
        <Hanyu>ruo</Hanyu>
        <Wade>jo</Wade>
        <MPSII>ruo</MPSII>
        <Yale>rwo</Yale>
        <Tongyong>ruo</Tongyong>
        <Phonetic>ㄖㄨㄛ</Phonetic>
    </item>
    <item>
        <Hanyu>sa</Hanyu>
        <Wade>sa</Wade>
        <MPSII>sa</MPSII>
        <Yale>sa</Yale>
        <Tongyong>sa</Tongyong>
        <Phonetic>ㄙㄚ</Phonetic>
    </item>
    <item>
        <Hanyu>sai</Hanyu>
        <Wade>sai</Wade>
        <MPSII>sai</MPSII>
        <Yale>sai</Yale>
        <Tongyong>sai</Tongyong>
        <Phonetic>ㄙㄞ</Phonetic>
    </item>
    <item>
        <Hanyu>san</Hanyu>
        <Wade>san</Wade>
        <MPSII>san</MPSII>
        <Yale>san</Yale>
        <Tongyong>san</Tongyong>
        <Phonetic>ㄙㄢ</Phonetic>
    </item>
    <item>
        <Hanyu>sang</Hanyu>
        <Wade>sang</Wade>
        <MPSII>sang</MPSII>
        <Yale>sang</Yale>
        <Tongyong>sang</Tongyong>
        <Phonetic>ㄙㄤ</Phonetic>
    </item>
    <item>
        <Hanyu>sao</Hanyu>
        <Wade>sao</Wade>
        <MPSII>sau</MPSII>
        <Yale>sau</Yale>
        <Tongyong>sao</Tongyong>
        <Phonetic>ㄙㄠ</Phonetic>
    </item>
    <item>
        <Hanyu>se</Hanyu>
        <Wade>se</Wade>
        <MPSII>se</MPSII>
        <Yale>se</Yale>
        <Tongyong>se</Tongyong>
        <Phonetic>ㄙㄜ</Phonetic>
    </item>
    <item>
        <Hanyu>sei</Hanyu>
        <Wade>sei</Wade>
        <MPSII>sei</MPSII>
        <Yale>sei</Yale>
        <Tongyong>sei</Tongyong>
        <Phonetic>ㄙㄟ</Phonetic>
    </item>
    <item>
        <Hanyu>sen</Hanyu>
        <Wade>sen</Wade>
        <MPSII>sen</MPSII>
        <Yale>sen</Yale>
        <Tongyong>sen</Tongyong>
        <Phonetic>ㄙㄣ</Phonetic>
    </item>
    <item>
        <Hanyu>seng</Hanyu>
        <Wade>seng</Wade>
        <MPSII>seng</MPSII>
        <Yale>seng</Yale>
        <Tongyong>seng</Tongyong>
        <Phonetic>ㄙㄥ</Phonetic>
    </item>
    <item>
        <Hanyu>sha</Hanyu>
        <Wade>sha</Wade>
        <MPSII>sha</MPSII>
        <Yale>sha</Yale>
        <Tongyong>sha</Tongyong>
        <Phonetic>ㄕㄚ</Phonetic>
    </item>
    <item>
        <Hanyu>shai</Hanyu>
        <Wade>shai</Wade>
        <MPSII>shai</MPSII>
        <Yale>shai</Yale>
        <Tongyong>shai</Tongyong>
        <Phonetic>ㄕㄞ</Phonetic>
    </item>
    <item>
        <Hanyu>shan</Hanyu>
        <Wade>shan</Wade>
        <MPSII>shan</MPSII>
        <Yale>shan</Yale>
        <Tongyong>shan</Tongyong>
        <Phonetic>ㄕㄢ</Phonetic>
    </item>
    <item>
        <Hanyu>shang</Hanyu>
        <Wade>shang</Wade>
        <MPSII>shang</MPSII>
        <Yale>shang</Yale>
        <Tongyong>shang</Tongyong>
        <Phonetic>ㄕㄤ</Phonetic>
    </item>
    <item>
        <Hanyu>shao</Hanyu>
        <Wade>shao</Wade>
        <MPSII>shau</MPSII>
        <Yale>shau</Yale>
        <Tongyong>shao</Tongyong>
        <Phonetic>ㄕㄠ</Phonetic>
    </item>
    <item>
        <Hanyu>she</Hanyu>
        <Wade>she</Wade>
        <MPSII>she</MPSII>
        <Yale>she</Yale>
        <Tongyong>she</Tongyong>
        <Phonetic>ㄕㄜ</Phonetic>
    </item>
    <item>
        <Hanyu>shei</Hanyu>
        <Wade>shei</Wade>
        <MPSII>shei</MPSII>
        <Yale>shei</Yale>
        <Tongyong>shei</Tongyong>
        <Phonetic>ㄕㄟ</Phonetic>
    </item>
    <item>
        <Hanyu>shen</Hanyu>
        <Wade>shen</Wade>
        <MPSII>shen</MPSII>
        <Yale>shen</Yale>
        <Tongyong>shen</Tongyong>
        <Phonetic>ㄕㄣ</Phonetic>
    </item>
    <item>
        <Hanyu>sheng</Hanyu>
        <Wade>sheng</Wade>
        <MPSII>sheng</MPSII>
        <Yale>sheng</Yale>
        <Tongyong>sheng</Tongyong>
        <Phonetic>ㄕㄥ</Phonetic>
    </item>
    <item>
        <Hanyu>shi</Hanyu>
        <Wade>shih</Wade>
        <MPSII>shr</MPSII>
        <Yale>shr</Yale>
        <Tongyong>shih</Tongyong>
        <Phonetic>ㄕ</Phonetic>
    </item>
    <item>
        <Hanyu>shong</Hanyu>
        <Wade>shung</Wade>
        <MPSII>shung</MPSII>
        <Yale>shung</Yale>
        <Tongyong>shong</Tongyong>
        <Phonetic>ㄕㄨㄥ</Phonetic>
    </item>
    <item>
        <Hanyu>shou</Hanyu>
        <Wade>shou</Wade>
        <MPSII>shou</MPSII>
        <Yale>shou</Yale>
        <Tongyong>shou</Tongyong>
        <Phonetic>ㄕㄡ</Phonetic>
    </item>
    <item>
        <Hanyu>shu</Hanyu>
        <Wade>shu</Wade>
        <MPSII>shu</MPSII>
        <Yale>shu</Yale>
        <Tongyong>shu</Tongyong>
        <Phonetic>ㄕㄨ</Phonetic>
    </item>
    <item>
        <Hanyu>shua</Hanyu>
        <Wade>shua</Wade>
        <MPSII>shua</MPSII>
        <Yale>shwa</Yale>
        <Tongyong>shua</Tongyong>
        <Phonetic>ㄕㄨㄚ</Phonetic>
    </item>
    <item>
        <Hanyu>shuai</Hanyu>
        <Wade>shuai</Wade>
        <MPSII>shuai</MPSII>
        <Yale>shwai</Yale>
        <Tongyong>shuai</Tongyong>
        <Phonetic>ㄕㄨㄞ</Phonetic>
    </item>
    <item>
        <Hanyu>shuan</Hanyu>
        <Wade>shuan</Wade>
        <MPSII>shuan</MPSII>
        <Yale>shwan</Yale>
        <Tongyong>shuan</Tongyong>
        <Phonetic>ㄕㄨㄢ</Phonetic>
    </item>
    <item>
        <Hanyu>shuang</Hanyu>
        <Wade>shuang</Wade>
        <MPSII>shuang</MPSII>
        <Yale>shwang</Yale>
        <Tongyong>shuang</Tongyong>
        <Phonetic>ㄕㄨㄤ</Phonetic>
    </item>
    <item>
        <Hanyu>shui</Hanyu>
        <Wade>shui</Wade>
        <MPSII>shuei</MPSII>
        <Yale>shwei</Yale>
        <Tongyong>shuei</Tongyong>
        <Phonetic>ㄕㄨㄟ</Phonetic>
    </item>
    <item>
        <Hanyu>shun</Hanyu>
        <Wade>shun</Wade>
        <MPSII>shuen</MPSII>
        <Yale>shwun</Yale>
        <Tongyong>shun</Tongyong>
        <Phonetic>ㄕㄨㄣ</Phonetic>
    </item>
    <item>
        <Hanyu>shuo</Hanyu>
        <Wade>shuo</Wade>
        <MPSII>shuo</MPSII>
        <Yale>shwo</Yale>
        <Tongyong>shuo</Tongyong>
        <Phonetic>ㄕㄨㄛ</Phonetic>
    </item>
    <item>
        <Hanyu>xi</Hanyu>
        <Wade>hsi</Wade>
        <MPSII>shi</MPSII>
        <Yale>syi</Yale>
        <Tongyong>si</Tongyong>
        <Phonetic>ㄒㄧ</Phonetic>
    </item>
    <item>
        <Hanyu>xia</Hanyu>
        <Wade>hsia</Wade>
        <MPSII>shia</MPSII>
        <Yale>sya</Yale>
        <Tongyong>sia</Tongyong>
        <Phonetic>ㄒㄧㄚ</Phonetic>
    </item>
    <item>
        <Hanyu>xian</Hanyu>
        <Wade>hsien</Wade>
        <MPSII>shian</MPSII>
        <Yale>syan</Yale>
        <Tongyong>sian</Tongyong>
        <Phonetic>ㄒㄧㄢ</Phonetic>
    </item>
    <item>
        <Hanyu>xiang</Hanyu>
        <Wade>hsiang</Wade>
        <MPSII>shiang</MPSII>
        <Yale>syang</Yale>
        <Tongyong>siang</Tongyong>
        <Phonetic>ㄒㄧㄤ</Phonetic>
    </item>
    <item>
        <Hanyu>xiao</Hanyu>
        <Wade>hsiao</Wade>
        <MPSII>shiau</MPSII>
        <Yale>syau</Yale>
        <Tongyong>siao</Tongyong>
        <Phonetic>ㄒㄧㄠ</Phonetic>
    </item>
    <item>
        <Hanyu>xie</Hanyu>
        <Wade>hsieh</Wade>
        <MPSII>shie</MPSII>
        <Yale>sye</Yale>
        <Tongyong>sie</Tongyong>
        <Phonetic>ㄒㄧㄝ</Phonetic>
    </item>
    <item>
        <Hanyu>si</Hanyu>
        <Wade>ssu</Wade>
        <MPSII>sz</MPSII>
        <Yale>sz</Yale>
        <Tongyong>sih</Tongyong>
        <Phonetic>ㄙ</Phonetic>
    </item>
    <item>
        <Hanyu>xin</Hanyu>
        <Wade>hsin</Wade>
        <MPSII>shin</MPSII>
        <Yale>syin</Yale>
        <Tongyong>sin</Tongyong>
        <Phonetic>ㄒㄧㄣ</Phonetic>
    </item>
    <item>
        <Hanyu>xing</Hanyu>
        <Wade>hsing</Wade>
        <MPSII>shing</MPSII>
        <Yale>sying</Yale>
        <Tongyong>sing</Tongyong>
        <Phonetic>ㄒㄧㄥ</Phonetic>
    </item>
    <item>
        <Hanyu>xiu</Hanyu>
        <Wade>hsiu</Wade>
        <MPSII>shiou</MPSII>
        <Yale>syou</Yale>
        <Tongyong>siou</Tongyong>
        <Phonetic>ㄒㄧㄡ</Phonetic>
    </item>
    <item>
        <Hanyu>song</Hanyu>
        <Wade>sung</Wade>
        <MPSII>sung</MPSII>
        <Yale>sung</Yale>
        <Tongyong>song</Tongyong>
        <Phonetic>ㄙㄨㄥ</Phonetic>
    </item>
    <item>
        <Hanyu>sou</Hanyu>
        <Wade>sou</Wade>
        <MPSII>sou</MPSII>
        <Yale>sou</Yale>
        <Tongyong>sou</Tongyong>
        <Phonetic>ㄙㄡ</Phonetic>
    </item>
    <item>
        <Hanyu>su</Hanyu>
        <Wade>su</Wade>
        <MPSII>su</MPSII>
        <Yale>su</Yale>
        <Tongyong>su</Tongyong>
        <Phonetic>ㄙㄨ</Phonetic>
    </item>
    <item>
        <Hanyu>suan</Hanyu>
        <Wade>suan</Wade>
        <MPSII>suan</MPSII>
        <Yale>swan</Yale>
        <Tongyong>suan</Tongyong>
        <Phonetic>ㄙㄨㄢ</Phonetic>
    </item>
    <item>
        <Hanyu>sui</Hanyu>
        <Wade>sui</Wade>
        <MPSII>suei</MPSII>
        <Yale>swei</Yale>
        <Tongyong>suei</Tongyong>
        <Phonetic>ㄙㄨㄟ</Phonetic>
    </item>
    <item>
        <Hanyu>sun</Hanyu>
        <Wade>sun</Wade>
        <MPSII>suen</MPSII>
        <Yale>swen</Yale>
        <Tongyong>sun</Tongyong>
        <Phonetic>ㄙㄨㄣ</Phonetic>
    </item>
    <item>
        <Hanyu>suo</Hanyu>
        <Wade>so</Wade>
        <MPSII>suo</MPSII>
        <Yale>swo</Yale>
        <Tongyong>suo</Tongyong>
        <Phonetic>ㄙㄨㄛ</Phonetic>
    </item>
    <item>
        <Hanyu>xiong</Hanyu>
        <Wade>hsiung</Wade>
        <MPSII>shiung</MPSII>
        <Yale>syung</Yale>
        <Tongyong>syong</Tongyong>
        <Phonetic>ㄒㄩㄥ</Phonetic>
    </item>
    <item>
        <Hanyu>xu</Hanyu>
        <Wade>hsu:</Wade>
        <MPSII>shiu</MPSII>
        <Yale>syu</Yale>
        <Tongyong>syu</Tongyong>
        <Phonetic>ㄒㄩ</Phonetic>
    </item>
    <item>
        <Hanyu>xuan</Hanyu>
        <Wade>hsu:an</Wade>
        <MPSII>shiuan</MPSII>
        <Yale>sywan</Yale>
        <Tongyong>syuan</Tongyong>
        <Phonetic>ㄒㄨㄢ</Phonetic>
    </item>
    <item>
        <Hanyu>xue</Hanyu>
        <Wade>hsu:eh</Wade>
        <MPSII>shiue</MPSII>
        <Yale>sywe</Yale>
        <Tongyong>syue</Tongyong>
        <Phonetic>ㄒㄩㄜ</Phonetic>
    </item>
    <item>
        <Hanyu>xun</Hanyu>
        <Wade>hsu:n</Wade>
        <MPSII>shiun</MPSII>
        <Yale>syun</Yale>
        <Tongyong>syun</Tongyong>
        <Phonetic>ㄒㄩㄋ</Phonetic>
    </item>
    <item>
        <Hanyu>ta</Hanyu>
        <Wade>t`a</Wade>
        <MPSII>ta</MPSII>
        <Yale>ta</Yale>
        <Tongyong>ta</Tongyong>
        <Phonetic>ㄊㄚ</Phonetic>
    </item>
    <item>
        <Hanyu>tai</Hanyu>
        <Wade>t`ai</Wade>
        <MPSII>tai</MPSII>
        <Yale>tai</Yale>
        <Tongyong>tai</Tongyong>
        <Phonetic>ㄊㄞ</Phonetic>
    </item>
    <item>
        <Hanyu>tan</Hanyu>
        <Wade>t`an</Wade>
        <MPSII>tan</MPSII>
        <Yale>tan</Yale>
        <Tongyong>tan</Tongyong>
        <Phonetic>ㄊㄢ</Phonetic>
    </item>
    <item>
        <Hanyu>tang</Hanyu>
        <Wade>t`ang</Wade>
        <MPSII>tang</MPSII>
        <Yale>tang</Yale>
        <Tongyong>tang</Tongyong>
        <Phonetic>ㄊㄤ</Phonetic>
    </item>
    <item>
        <Hanyu>tao</Hanyu>
        <Wade>t`ao</Wade>
        <MPSII>tau</MPSII>
        <Yale>tau</Yale>
        <Tongyong>tao</Tongyong>
        <Phonetic>ㄊㄠ</Phonetic>
    </item>
    <item>
        <Hanyu>te</Hanyu>
        <Wade>t`e</Wade>
        <MPSII>te</MPSII>
        <Yale>te</Yale>
        <Tongyong>te</Tongyong>
        <Phonetic>ㄊㄜ</Phonetic>
    </item>
    <item>
        <Hanyu>teng</Hanyu>
        <Wade>t`eng</Wade>
        <MPSII>teng</MPSII>
        <Yale>teng</Yale>
        <Tongyong>teng</Tongyong>
        <Phonetic>ㄊㄥ</Phonetic>
    </item>
    <item>
        <Hanyu>ti</Hanyu>
        <Wade>t`i</Wade>
        <MPSII>ti</MPSII>
        <Yale>ti</Yale>
        <Tongyong>ti</Tongyong>
        <Phonetic>ㄊㄧ</Phonetic>
    </item>
    <item>
        <Hanyu>tian</Hanyu>
        <Wade>t`ien</Wade>
        <MPSII>tian</MPSII>
        <Yale>tyan</Yale>
        <Tongyong>tian</Tongyong>
        <Phonetic>ㄊㄧㄢ</Phonetic>
    </item>
    <item>
        <Hanyu>tiao</Hanyu>
        <Wade>t`iao</Wade>
        <MPSII>tiau</MPSII>
        <Yale>tyau</Yale>
        <Tongyong>tiao</Tongyong>
        <Phonetic>ㄊㄧㄠ</Phonetic>
    </item>
    <item>
        <Hanyu>tie</Hanyu>
        <Wade>t`ieh</Wade>
        <MPSII>tie</MPSII>
        <Yale>tye</Yale>
        <Tongyong>tie</Tongyong>
        <Phonetic>ㄊㄧㄝ</Phonetic>
    </item>
    <item>
        <Hanyu>ting</Hanyu>
        <Wade>t`ing</Wade>
        <MPSII>ting</MPSII>
        <Yale>ting</Yale>
        <Tongyong>ting</Tongyong>
        <Phonetic>ㄊㄧㄥ</Phonetic>
    </item>
    <item>
        <Hanyu>tong</Hanyu>
        <Wade>t`ung</Wade>
        <MPSII>tung</MPSII>
        <Yale>tung</Yale>
        <Tongyong>tong</Tongyong>
        <Phonetic>ㄊㄨㄥ</Phonetic>
    </item>
    <item>
        <Hanyu>tou</Hanyu>
        <Wade>t`ou</Wade>
        <MPSII>tou</MPSII>
        <Yale>tou</Yale>
        <Tongyong>tou</Tongyong>
        <Phonetic>ㄊㄡ</Phonetic>
    </item>
    <item>
        <Hanyu>tu</Hanyu>
        <Wade>t`u</Wade>
        <MPSII>tu</MPSII>
        <Yale>tu</Yale>
        <Tongyong>tu</Tongyong>
        <Phonetic>ㄊㄨ</Phonetic>
    </item>
    <item>
        <Hanyu>tuan</Hanyu>
        <Wade>t`uan</Wade>
        <MPSII>tuan</MPSII>
        <Yale>twan</Yale>
        <Tongyong>tuan</Tongyong>
        <Phonetic>ㄊㄨㄢ</Phonetic>
    </item>
    <item>
        <Hanyu>tui</Hanyu>
        <Wade>t`ui</Wade>
        <MPSII>tuei</MPSII>
        <Yale>twei</Yale>
        <Tongyong>tuei</Tongyong>
        <Phonetic>ㄊㄨㄟ</Phonetic>
    </item>
    <item>
        <Hanyu>tun</Hanyu>
        <Wade>t`un</Wade>
        <MPSII>tuen</MPSII>
        <Yale>twen</Yale>
        <Tongyong>tun</Tongyong>
        <Phonetic>ㄊㄨㄣ</Phonetic>
    </item>
    <item>
        <Hanyu>tuo</Hanyu>
        <Wade>t`o</Wade>
        <MPSII>tuo</MPSII>
        <Yale>two</Yale>
        <Tongyong>tuo</Tongyong>
        <Phonetic>ㄊㄨㄛ</Phonetic>
    </item>
    <item>
        <Hanyu>wa</Hanyu>
        <Wade>wa</Wade>
        <MPSII>wa</MPSII>
        <Yale>wa</Yale>
        <Tongyong>wa</Tongyong>
        <Phonetic>ㄨㄚ</Phonetic>
    </item>
    <item>
        <Hanyu>wai</Hanyu>
        <Wade>wai</Wade>
        <MPSII>wai</MPSII>
        <Yale>wai</Yale>
        <Tongyong>wai</Tongyong>
        <Phonetic>ㄨㄞ</Phonetic>
    </item>
    <item>
        <Hanyu>wan</Hanyu>
        <Wade>wan</Wade>
        <MPSII>wan</MPSII>
        <Yale>wan</Yale>
        <Tongyong>wan</Tongyong>
        <Phonetic>ㄨㄢ</Phonetic>
    </item>
    <item>
        <Hanyu>wang</Hanyu>
        <Wade>wang</Wade>
        <MPSII>wang</MPSII>
        <Yale>wang</Yale>
        <Tongyong>wang</Tongyong>
        <Phonetic>ㄨㄤ</Phonetic>
    </item>
    <item>
        <Hanyu>wei</Hanyu>
        <Wade>wei</Wade>
        <MPSII>wei</MPSII>
        <Yale>wei</Yale>
        <Tongyong>wei</Tongyong>
        <Phonetic>ㄨㄟ</Phonetic>
    </item>
    <item>
        <Hanyu>wo</Hanyu>
        <Wade>wo</Wade>
        <MPSII>wo</MPSII>
        <Yale>wo</Yale>
        <Tongyong>wo</Tongyong>
        <Phonetic>ㄨㄛ</Phonetic>
    </item>
    <item>
        <Hanyu>weng</Hanyu>
        <Wade>weng</Wade>
        <MPSII>weng</MPSII>
        <Yale>weng</Yale>
        <Tongyong>wong</Tongyong>
        <Phonetic>ㄨㄥ</Phonetic>
    </item>
    <item>
        <Hanyu>wu</Hanyu>
        <Wade>wu</Wade>
        <MPSII>wu</MPSII>
        <Yale>wu</Yale>
        <Tongyong>wu</Tongyong>
        <Phonetic>ㄨ</Phonetic>
    </item>
    <item>
        <Hanyu>wen</Hanyu>
        <Wade>wen</Wade>
        <MPSII>wen</MPSII>
        <Yale>wen</Yale>
        <Tongyong>wun</Tongyong>
        <Phonetic>ㄨㄣ</Phonetic>
    </item>
    <item>
        <Hanyu>ya</Hanyu>
        <Wade>ya</Wade>
        <MPSII>ya</MPSII>
        <Yale>ya</Yale>
        <Tongyong>ya</Tongyong>
        <Phonetic>ㄧㄚ</Phonetic>
    </item>
    <item>
        <Hanyu>yan</Hanyu>
        <Wade>yan</Wade>
        <MPSII>yan</MPSII>
        <Yale>yan</Yale>
        <Tongyong>yan</Tongyong>
        <Phonetic>ㄧㄢ</Phonetic>
    </item>
    <item>
        <Hanyu>yang</Hanyu>
        <Wade>yang</Wade>
        <MPSII>yang</MPSII>
        <Yale>yang</Yale>
        <Tongyong>yang</Tongyong>
        <Phonetic>ㄧㄤ</Phonetic>
    </item>
    <item>
        <Hanyu>yao</Hanyu>
        <Wade>yao</Wade>
        <MPSII>yau</MPSII>
        <Yale>yau</Yale>
        <Tongyong>yao</Tongyong>
        <Phonetic>ㄧㄠ</Phonetic>
    </item>
    <item>
        <Hanyu>ye</Hanyu>
        <Wade>yeh</Wade>
        <MPSII>ye</MPSII>
        <Yale>ye</Yale>
        <Tongyong>ye</Tongyong>
        <Phonetic>ㄧㄝ</Phonetic>
    </item>
    <item>
        <Hanyu>yi</Hanyu>
        <Wade>i</Wade>
        <MPSII>yi</MPSII>
        <Yale>yi</Yale>
        <Tongyong>yi</Tongyong>
        <Phonetic>ㄧ</Phonetic>
    </item>
    <item>
        <Hanyu>yin</Hanyu>
        <Wade>yin</Wade>
        <MPSII>yin</MPSII>
        <Yale>yin</Yale>
        <Tongyong>yin</Tongyong>
        <Phonetic>ㄧㄣ</Phonetic>
    </item>
    <item>
        <Hanyu>ying</Hanyu>
        <Wade>ying</Wade>
        <MPSII>ying</MPSII>
        <Yale>ying</Yale>
        <Tongyong>ying</Tongyong>
        <Phonetic>ㄧㄥ</Phonetic>
    </item>
    <item>
        <Hanyu>yong</Hanyu>
        <Wade>yung</Wade>
        <MPSII>yung</MPSII>
        <Yale>yung</Yale>
        <Tongyong>yong</Tongyong>
        <Phonetic>ㄩㄥ</Phonetic>
    </item>
    <item>
        <Hanyu>you</Hanyu>
        <Wade>yu</Wade>
        <MPSII>you</MPSII>
        <Yale>you</Yale>
        <Tongyong>you</Tongyong>
        <Phonetic>ㄧㄡ</Phonetic>
    </item>
    <item>
        <Hanyu>yu</Hanyu>
        <Wade>yu:</Wade>
        <MPSII>yu</MPSII>
        <Yale>yu</Yale>
        <Tongyong>yu</Tongyong>
        <Phonetic>ㄩ</Phonetic>
    </item>
    <item>
        <Hanyu>yuan</Hanyu>
        <Wade>yu:an</Wade>
        <MPSII>yuan</MPSII>
        <Yale>ywan</Yale>
        <Tongyong>yuan</Tongyong>
        <Phonetic>ㄩㄢ</Phonetic>
    </item>
    <item>
        <Hanyu>yue</Hanyu>
        <Wade>yu:eh</Wade>
        <MPSII>yue</MPSII>
        <Yale>ywe</Yale>
        <Tongyong>yue</Tongyong>
        <Phonetic>ㄩㄝ</Phonetic>
    </item>
    <item>
        <Hanyu>yun</Hanyu>
        <Wade>yu:n</Wade>
        <MPSII>yun</MPSII>
        <Yale>yun</Yale>
        <Tongyong>yun</Tongyong>
        <Phonetic>ㄩㄣ</Phonetic>
    </item>
    <item>
        <Hanyu>za</Hanyu>
        <Wade>tsa</Wade>
        <MPSII>tza</MPSII>
        <Yale>dza</Yale>
        <Tongyong>za</Tongyong>
        <Phonetic>ㄗㄚ</Phonetic>
    </item>
    <item>
        <Hanyu>zai</Hanyu>
        <Wade>tsai</Wade>
        <MPSII>tzai</MPSII>
        <Yale>dzai</Yale>
        <Tongyong>zai</Tongyong>
        <Phonetic>ㄗㄞ</Phonetic>
    </item>
    <item>
        <Hanyu>zan</Hanyu>
        <Wade>tsan</Wade>
        <MPSII>tzan</MPSII>
        <Yale>dzan</Yale>
        <Tongyong>zan</Tongyong>
        <Phonetic>ㄗㄢ</Phonetic>
    </item>
    <item>
        <Hanyu>zang</Hanyu>
        <Wade>tsang</Wade>
        <MPSII>tzang</MPSII>
        <Yale>dzang</Yale>
        <Tongyong>zang</Tongyong>
        <Phonetic>ㄗㄤ</Phonetic>
    </item>
    <item>
        <Hanyu>zao</Hanyu>
        <Wade>tsao</Wade>
        <MPSII>tzau</MPSII>
        <Yale>dzau</Yale>
        <Tongyong>zao</Tongyong>
        <Phonetic>ㄗㄠ</Phonetic>
    </item>
    <item>
        <Hanyu>ze</Hanyu>
        <Wade>tse</Wade>
        <MPSII>tze</MPSII>
        <Yale>dze</Yale>
        <Tongyong>ze</Tongyong>
        <Phonetic>ㄗㄜ</Phonetic>
    </item>
    <item>
        <Hanyu>zei</Hanyu>
        <Wade>tsei</Wade>
        <MPSII>tzei</MPSII>
        <Yale>dzei</Yale>
        <Tongyong>zei</Tongyong>
        <Phonetic>ㄗㄟ</Phonetic>
    </item>
    <item>
        <Hanyu>zen</Hanyu>
        <Wade>tsen</Wade>
        <MPSII>tzen</MPSII>
        <Yale>dzen</Yale>
        <Tongyong>zen</Tongyong>
        <Phonetic>ㄗㄣ</Phonetic>
    </item>
    <item>
        <Hanyu>zeng</Hanyu>
        <Wade>tseng</Wade>
        <MPSII>tzeng</MPSII>
        <Yale>dzeng</Yale>
        <Tongyong>zeng</Tongyong>
        <Phonetic>ㄗㄥ</Phonetic>
    </item>
    <item>
        <Hanyu>zi</Hanyu>
        <Wade>tzu</Wade>
        <MPSII>tz</MPSII>
        <Yale>dz</Yale>
        <Tongyong>zih</Tongyong>
        <Phonetic>ㄗ</Phonetic>
    </item>
    <item>
        <Hanyu>zong</Hanyu>
        <Wade>tsung</Wade>
        <MPSII>tzung</MPSII>
        <Yale>dzung</Yale>
        <Tongyong>zong</Tongyong>
        <Phonetic>ㄗㄨㄥ</Phonetic>
    </item>
    <item>
        <Hanyu>zou</Hanyu>
        <Wade>tsou</Wade>
        <MPSII>tzou</MPSII>
        <Yale>dzou</Yale>
        <Tongyong>zou</Tongyong>
        <Phonetic>ㄗㄡ</Phonetic>
    </item>
    <item>
        <Hanyu>zu</Hanyu>
        <Wade>tsu</Wade>
        <MPSII>tzu</MPSII>
        <Yale>dzu</Yale>
        <Tongyong>zu</Tongyong>
        <Phonetic>ㄗㄨ</Phonetic>
    </item>
    <item>
        <Hanyu>zuan</Hanyu>
        <Wade>tsuan</Wade>
        <MPSII>tzuan</MPSII>
        <Yale>dzwan</Yale>
        <Tongyong>zuan</Tongyong>
        <Phonetic>ㄗㄨㄢ</Phonetic>
    </item>
    <item>
        <Hanyu>zui</Hanyu>
        <Wade>tsui</Wade>
        <MPSII>tzuei</MPSII>
        <Yale>dzwei</Yale>
        <Tongyong>zuei</Tongyong>
        <Phonetic>ㄗㄨㄟ</Phonetic>
    </item>
    <item>
        <Hanyu>zun</Hanyu>
        <Wade>tsun</Wade>
        <MPSII>tzuen</MPSII>
        <Yale>dzwen</Yale>
        <Tongyong>zun</Tongyong>
        <Phonetic>ㄗㄨㄣ</Phonetic>
    </item>
    <item>
        <Hanyu>zuo</Hanyu>
        <Wade>tso</Wade>
        <MPSII>tzuo</MPSII>
        <Yale>dzwo</Yale>
        <Tongyong>zuo</Tongyong>
        <Phonetic>ㄗㄨㄛ</Phonetic>
    </item>
</pinyin_mapping>
